{"type": "Feature", "id": 12516596, "geometry": {"type": "Point", "coordinates": [118.0588, 50.031101]}, "properties": {"woe:id": 12516596, "woe:parent_id": 2121630, "woe:name": "Oktyabrskiy West Airport", "woe:placetype": 14, "woe:placetype_name": "Airport", "woe:lang": "ENG", "iso:country": "RU", "meta:provider": ["geoplanet:7.3.1", "geoplanet:7.3.2", "geoplanet:7.4.0", "geoplanet:7.4.1", "geoplanet:7.5.1", "geoplanet:7.5.2", "geoplanet:7.6.0", "geoplanet:7.8.1", "geoplanet:7.9.0", "geoplanet:7.10.0", "geoplanet:8.0.0", "woeplanet:8.0.0"], "meta:indexed": "2020-08-20T20:56:29.117782", "meta:updated": "2020-10-14T12:06:59.552913", "woe:hierarchy": {"continent": 24865671, "country": 23424936, "town": 0, "planet": 1, "county": 12598174, "suburb": 0, "state": 56437930, "region": 0, "localadmin": 0}, "woe:timezone_id": 28350865, "woe:hash": "y8guw7zu33jw", "woe:centroid": [118.0588, 50.031101], "geom:latitude": 50.031101, "geom:longitude": 118.0588, "geom:hash": "y8guw7zu33jw", "woe:latitude": 50.031101, "geom:centroid": [118.0588, 50.031101], "woe:longitude": 118.0588, "woe:repo": "woeplanet-airport-ru", "geom:area": 0.0, "woe:scale": 19}}