{"type": "Feature", "id": 12516711, "geometry": {"type": "Point", "coordinates": [131.395096, 44.4366]}, "properties": {"woe:id": 12516711, "woe:parent_id": 2068284, "woe:name": "Pogranichnyy Airport", "woe:placetype": 14, "woe:placetype_name": "Airport", "woe:lang": "ENG", "iso:country": "RU", "meta:provider": ["geoplanet:7.3.1", "geoplanet:7.3.2", "geoplanet:7.4.0", "geoplanet:7.4.1", "geoplanet:7.5.1", "geoplanet:7.5.2", "geoplanet:7.6.0", "geoplanet:7.8.1", "geoplanet:7.9.0", "geoplanet:7.10.0", "geoplanet:8.0.0", "woeplanet:8.0.0"], "meta:indexed": "2020-08-20T20:56:29.211697", "meta:updated": "2020-10-14T12:06:58.925859", "woe:hierarchy": {"continent": 24865671, "country": 23424936, "town": 0, "planet": 1, "county": 12597925, "suburb": 0, "state": 2346886, "region": 0, "localadmin": 0}, "woe:timezone_id": 56043609, "woe:hash": "wzvkvcqvzwsu", "woe:centroid": [131.395096, 44.4366], "geom:latitude": 44.4366, "geom:longitude": 131.395096, "geom:hash": "wzvkvcqvzwsu", "woe:latitude": 44.4366, "geom:centroid": [131.395096, 44.4366], "woe:longitude": 131.395096, "woe:repo": "woeplanet-airport-ru", "geom:area": 0.0, "woe:scale": 19}}