{"type": "Feature", "id": 12517122, "geometry": {"type": "Point", "coordinates": [57.667, 64.443298]}, "properties": {"woe:id": 12517122, "woe:parent_id": 2101838, "woe:name": "Ust Voya Airport", "woe:placetype": 14, "woe:placetype_name": "Airport", "woe:lang": "ENG", "iso:country": "RU", "meta:provider": ["geoplanet:7.3.1", "geoplanet:7.3.2", "geoplanet:7.4.0", "geoplanet:7.4.1", "geoplanet:7.5.1", "geoplanet:7.5.2", "geoplanet:7.6.0", "geoplanet:7.8.1", "geoplanet:7.9.0", "geoplanet:7.10.0", "geoplanet:8.0.0", "woeplanet:8.0.0"], "meta:indexed": "2020-08-20T20:56:29.563863", "meta:updated": "2020-10-14T12:06:58.985252", "woe:hierarchy": {"continent": 24865671, "country": 23424936, "town": 0, "planet": 1, "county": 12597466, "suburb": 0, "state": 2346874, "region": 0, "localadmin": 0}, "woe:timezone_id": 56043614, "woe:hash": "v73n85xc6mry", "woe:centroid": [57.667, 64.443298], "geom:latitude": 64.443298, "geom:longitude": 57.667, "geom:hash": "v73n85xc6mry", "woe:latitude": 64.443298, "geom:centroid": [57.667, 64.443298], "woe:longitude": 57.667, "woe:repo": "woeplanet-airport-ru", "geom:area": 0.0, "woe:scale": 19}}