{"type": "Feature", "id": 12516852, "properties": {"woe:id": 12516852, "woe:parent_id": 2081575, "woe:name": "Sharypovo Airport", "woe:placetype": 14, "woe:placetype_name": "Airport", "woe:lang": "ENG", "iso:country": "RU", "meta:provider": ["geoplanet:7.3.1", "geoplanet:7.3.2", "geoplanet:7.4.0", "geoplanet:7.4.1", "geoplanet:7.5.1", "geoplanet:7.5.2", "geoplanet:7.6.0", "geoplanet:7.8.1", "geoplanet:7.9.0", "geoplanet:7.10.0", "geoplanet:8.0.0", "woeplanet:8.0.0"], "meta:indexed": "2020-08-20T20:56:29.326866", "meta:updated": "2020-08-22T02:53:12.250041", "woe:hierarchy": {"continent": 24865671, "country": 23424936, "town": 0, "planet": 1, "county": 12597881, "suburb": 0, "state": 20070524, "region": 0, "localadmin": 0}, "woe:timezone_id": 28350837, "woe:hash": "vcz7yr737vmq", "woe:centroid": [89.224602, 55.542999], "geom:latitude": 55.542999, "geom:longitude": 89.224602, "geom:hash": "vcz7yr737vmq", "woe:latitude": 55.542999, "geom:centroid": [89.224602, 55.542999], "woe:longitude": 89.224602, "woe:repo": "woeplanet-airport-ru"}, "geometry": {"coordinates": [89.224602, 55.542999], "type": "Point"}}