{"type": "Feature", "id": 12516043, "geometry": {"type": "Point", "coordinates": [104.170403, 52.376099]}, "properties": {"woe:id": 12516043, "woe:parent_id": 2042574, "woe:name": "Irkutsk Northwest Airport", "woe:placetype": 14, "woe:placetype_name": "Airport", "woe:lang": "ENG", "iso:country": "RU", "meta:provider": ["geoplanet:7.3.1", "geoplanet:7.3.2", "geoplanet:7.4.0", "geoplanet:7.4.1", "geoplanet:7.5.1", "geoplanet:7.5.2", "geoplanet:7.6.0", "geoplanet:7.8.1", "geoplanet:7.9.0", "geoplanet:7.10.0", "geoplanet:8.0.0", "woeplanet:8.0.0"], "meta:indexed": "2020-08-20T20:56:28.611198", "meta:updated": "2020-10-14T12:06:59.094256", "woe:hierarchy": {"continent": 24865671, "country": 23424936, "town": 0, "planet": 1, "county": 12598263, "suburb": 0, "state": 2346896, "region": 0, "localadmin": 0}, "woe:timezone_id": 28350829, "woe:hash": "y361fqy8fkd2", "woe:centroid": [104.170403, 52.376099], "geom:latitude": 52.376099, "geom:longitude": 104.170403, "geom:hash": "y361fqy8fkd2", "woe:latitude": 52.376099, "geom:centroid": [104.170403, 52.376099], "woe:longitude": 104.170403, "woe:repo": "woeplanet-airport-ru", "geom:area": 0.0, "woe:scale": 19}}