{"type": "Feature", "id": 12516001, "geometry": {"type": "Point", "coordinates": [47.7691, 61.247002]}, "properties": {"woe:id": 12516001, "woe:parent_id": 2051610, "woe:name": "Gorbachika Northwest Airport", "woe:placetype": 14, "woe:placetype_name": "Airport", "woe:lang": "ENG", "iso:country": "RU", "meta:provider": ["geoplanet:7.3.1", "geoplanet:7.3.2", "geoplanet:7.4.0", "geoplanet:7.4.1", "geoplanet:7.5.1", "geoplanet:7.5.2", "geoplanet:7.6.0", "geoplanet:7.8.1", "geoplanet:7.9.0", "geoplanet:7.10.0", "geoplanet:8.0.0", "woeplanet:8.0.0"], "meta:indexed": "2020-08-20T20:56:28.571989", "meta:updated": "2020-10-14T12:06:59.069705", "woe:hierarchy": {"continent": 24865671, "country": 23424936, "town": 0, "planet": 1, "county": 12598035, "suburb": 0, "state": 20070508, "region": 0, "localadmin": 0}, "woe:timezone_id": 56043614, "woe:hash": "v4curj8mssww", "woe:centroid": [47.7691, 61.247002], "geom:latitude": 61.247002, "geom:longitude": 47.7691, "geom:hash": "v4curj8mssww", "woe:latitude": 61.247002, "geom:centroid": [47.7691, 61.247002], "woe:longitude": 47.7691, "woe:repo": "woeplanet-airport-ru", "geom:area": 0.0, "woe:scale": 19}}