{"type": "Feature", "id": 12516562, "properties": {"woe:id": 12516562, "woe:parent_id": 2055965, "woe:name": "Novosergiyevskaya Airport", "woe:placetype": 14, "woe:placetype_name": "Airport", "woe:lang": "ENG", "iso:country": "RU", "meta:provider": ["geoplanet:7.3.1", "geoplanet:7.3.2", "geoplanet:7.4.0", "geoplanet:7.4.1", "geoplanet:7.5.1", "geoplanet:7.5.2", "geoplanet:7.6.0", "geoplanet:7.8.1", "geoplanet:7.9.0", "geoplanet:7.10.0", "geoplanet:8.0.0", "woeplanet:8.0.0"], "meta:indexed": "2020-08-20T20:56:29.090031", "meta:updated": "2020-08-22T02:53:12.141706", "woe:hierarchy": {"continent": 24865671, "country": 23424936, "town": 0, "planet": 1, "county": 12599115, "suburb": 0, "state": 2346884, "region": 0, "localadmin": 0}, "woe:timezone_id": 56043614, "woe:hash": "ubk26f9w5pbc", "woe:centroid": [39.849602, 46.465], "geom:latitude": 46.465, "geom:longitude": 39.849602, "geom:hash": "ubk26f9w5pbc", "woe:latitude": 46.465, "geom:centroid": [39.849602, 46.465], "woe:longitude": 39.849602, "woe:repo": "woeplanet-airport-ru"}, "geometry": {"coordinates": [39.849602, 46.465], "type": "Point"}}