{"type": "Feature", "id": 12516126, "properties": {"woe:id": 12516126, "woe:parent_id": 2121289, "woe:name": "Kerchevskiy Airport", "woe:placetype": 14, "woe:placetype_name": "Airport", "woe:lang": "ENG", "iso:country": "RU", "meta:provider": ["geoplanet:7.3.1", "geoplanet:7.3.2", "geoplanet:7.4.0", "geoplanet:7.4.1", "geoplanet:7.5.1", "geoplanet:7.5.2", "geoplanet:7.6.0", "geoplanet:7.8.1", "geoplanet:7.9.0", "geoplanet:7.10.0", "geoplanet:8.0.0", "woeplanet:8.0.0"], "meta:indexed": "2020-08-20T20:56:28.688589", "meta:updated": "2020-08-22T02:53:11.977960", "woe:hierarchy": {"continent": 24865671, "country": 23424936, "town": 0, "planet": 1, "county": 12599027, "suburb": 0, "state": 20070511, "region": 0, "localadmin": 0}, "woe:timezone_id": 28350866, "woe:hash": "v68j01uqq1k2", "woe:centroid": [56.2561, 59.952099], "geom:latitude": 59.952099, "geom:longitude": 56.2561, "geom:hash": "v68j01uqq1k2", "woe:latitude": 59.952099, "geom:centroid": [56.2561, 59.952099], "woe:longitude": 56.2561, "woe:repo": "woeplanet-airport-ru"}, "geometry": {"coordinates": [56.2561, 59.952099], "type": "Point"}}