{"type": "Feature", "id": 12516847, "geometry": {"type": "Point", "coordinates": [152.408798, 62.9216]}, "properties": {"woe:id": 12516847, "woe:parent_id": 2123381, "woe:name": "Seymchan Airport", "woe:placetype": 14, "woe:placetype_name": "Airport", "woe:lang": "ENG", "iso:country": "RU", "meta:provider": ["geoplanet:7.3.1", "geoplanet:7.3.2", "geoplanet:7.4.0", "geoplanet:7.4.1", "geoplanet:7.5.1", "geoplanet:7.5.2", "geoplanet:7.6.0", "geoplanet:7.8.1", "geoplanet:7.9.0", "geoplanet:7.10.0", "geoplanet:8.0.0", "woeplanet:8.0.0"], "meta:indexed": "2020-08-20T20:56:29.322813", "meta:updated": "2020-10-14T12:06:59.870222", "woe:hierarchy": {"continent": 24865671, "country": 23424936, "town": 0, "planet": 1, "county": 12598705, "suburb": 0, "state": 20070512, "region": 0, "localadmin": 0}, "woe:timezone_id": 28350841, "woe:hash": "z7hmuns8ykks", "woe:centroid": [152.408798, 62.9216], "geom:latitude": 62.9216, "geom:longitude": 152.408798, "geom:hash": "z7hmuns8ykks", "woe:latitude": 62.9216, "geom:centroid": [152.408798, 62.9216], "woe:longitude": 152.408798, "woe:repo": "woeplanet-airport-ru", "geom:area": 0.0, "woe:scale": 19}}