{"type": "Feature", "id": 12516651, "geometry": {"type": "Point", "coordinates": [37.570499, 54.626701]}, "properties": {"woe:id": 12516651, "woe:parent_id": 2062232, "woe:name": "Pakhomovo Airport", "woe:placetype": 14, "woe:placetype_name": "Airport", "woe:lang": "ENG", "iso:country": "RU", "meta:provider": ["geoplanet:7.3.1", "geoplanet:7.3.2", "geoplanet:7.4.0", "geoplanet:7.4.1", "geoplanet:7.5.1", "geoplanet:7.5.2", "geoplanet:7.6.0", "geoplanet:7.8.1", "geoplanet:7.9.0", "geoplanet:7.10.0", "geoplanet:8.0.0", "woeplanet:8.0.0"], "meta:indexed": "2020-08-20T20:56:29.163641", "meta:updated": "2020-10-14T12:06:59.439446", "woe:hierarchy": {"continent": 24865671, "country": 23424936, "town": 0, "planet": 1, "county": 12599436, "suburb": 0, "state": 2346929, "region": 0, "localadmin": 0}, "woe:timezone_id": 56043614, "woe:hash": "ucdwybqp854s", "woe:centroid": [37.570499, 54.626701], "geom:latitude": 54.626701, "geom:longitude": 37.570499, "geom:hash": "ucdwybqp854s", "woe:latitude": 54.626701, "geom:centroid": [37.570499, 54.626701], "woe:longitude": 37.570499, "woe:repo": "woeplanet-airport-ru", "geom:area": 0.0, "woe:scale": 19}}