{"type": "Feature", "id": 12516422, "geometry": {"type": "Point", "coordinates": [136.280197, 49.982601]}, "properties": {"woe:id": 12516422, "woe:parent_id": 2004260, "woe:name": "Mengon Airport", "woe:placetype": 14, "woe:placetype_name": "Airport", "woe:lang": "ENG", "iso:country": "RU", "meta:provider": ["geoplanet:7.3.1", "geoplanet:7.3.2", "geoplanet:7.4.0", "geoplanet:7.4.1", "geoplanet:7.5.1", "geoplanet:7.5.2", "geoplanet:7.6.0", "geoplanet:7.8.1", "geoplanet:7.9.0", "geoplanet:7.10.0", "geoplanet:8.0.0", "woeplanet:8.0.0"], "meta:indexed": "2020-08-20T20:56:28.965893", "meta:updated": "2020-10-14T12:06:59.776512", "woe:hierarchy": {"continent": 24865671, "country": 23424936, "town": 0, "planet": 1, "county": 12597736, "suburb": 0, "state": 2346883, "region": 0, "localadmin": 0}, "woe:timezone_id": 56043609, "woe:hash": "z0bum5h1yb0h", "woe:centroid": [136.280197, 49.982601], "geom:latitude": 49.982601, "geom:longitude": 136.280197, "geom:hash": "z0bum5h1yb0h", "woe:latitude": 49.982601, "geom:centroid": [136.280197, 49.982601], "woe:longitude": 136.280197, "woe:repo": "woeplanet-airport-ru", "geom:area": 0.0, "woe:scale": 19}}