{"type": "Feature", "id": 12516906, "geometry": {"type": "Point", "coordinates": [48.779099, 56.151199]}, "properties": {"woe:id": 12516906, "woe:parent_id": 2087694, "woe:name": "Sotnur Airport", "woe:placetype": 14, "woe:placetype_name": "Airport", "woe:lang": "ENG", "iso:country": "RU", "meta:provider": ["geoplanet:7.3.1", "geoplanet:7.3.2", "geoplanet:7.4.0", "geoplanet:7.4.1", "geoplanet:7.5.1", "geoplanet:7.5.2", "geoplanet:7.6.0", "geoplanet:7.8.1", "geoplanet:7.9.0", "geoplanet:7.10.0", "geoplanet:8.0.0", "woeplanet:8.0.0"], "meta:indexed": "2020-08-20T20:56:29.370345", "meta:updated": "2020-10-14T12:06:59.277865", "woe:hierarchy": {"continent": 24865671, "country": 23424936, "town": 0, "planet": 1, "county": 12597480, "suburb": 0, "state": 2346875, "region": 0, "localadmin": 0}, "woe:timezone_id": 56043614, "woe:hash": "v1fxmypb7qhm", "woe:centroid": [48.779099, 56.151199], "geom:latitude": 56.151199, "geom:longitude": 48.779099, "geom:hash": "v1fxmypb7qhm", "woe:latitude": 56.151199, "geom:centroid": [48.779099, 56.151199], "woe:longitude": 48.779099, "woe:repo": "woeplanet-airport-ru", "geom:area": 0.0, "woe:scale": 19}}