{"type": "Feature", "id": 12515995, "geometry": {"type": "Point", "coordinates": [160.567902, 61.841]}, "properties": {"woe:id": 12515995, "woe:parent_id": 1997121, "woe:name": "Gizhiga Airport", "woe:placetype": 14, "woe:placetype_name": "Airport", "woe:lang": "ENG", "iso:country": "RU", "meta:provider": ["geoplanet:7.3.1", "geoplanet:7.3.2", "geoplanet:7.4.0", "geoplanet:7.4.1", "geoplanet:7.5.1", "geoplanet:7.5.2", "geoplanet:7.6.0", "geoplanet:7.8.1", "geoplanet:7.9.0", "geoplanet:7.10.0", "geoplanet:8.0.0", "woeplanet:8.0.0"], "meta:indexed": "2020-08-20T20:56:28.566361", "meta:updated": "2020-10-14T12:06:58.889879", "woe:hierarchy": {"continent": 24865671, "country": 23424936, "town": 0, "planet": 1, "county": 12598703, "suburb": 0, "state": 20070512, "region": 0, "localadmin": 0}, "woe:timezone_id": 28350841, "woe:hash": "zdfpvccczmcw", "woe:centroid": [160.567902, 61.841], "geom:latitude": 61.841, "geom:longitude": 160.567902, "geom:hash": "zdfpvccczmcw", "woe:latitude": 61.841, "geom:centroid": [160.567902, 61.841], "woe:longitude": 160.567902, "woe:repo": "woeplanet-airport-ru", "geom:area": 0.0, "woe:scale": 19}}