{"type": "Feature", "id": 12516997, "geometry": {"type": "Point", "coordinates": [59.471699, 51.6012]}, "properties": {"woe:id": 12516997, "woe:parent_id": 2123879, "woe:name": "Terensay Airport", "woe:placetype": 14, "woe:placetype_name": "Airport", "woe:lang": "ENG", "iso:country": "RU", "meta:provider": ["geoplanet:7.3.1", "geoplanet:7.3.2", "geoplanet:7.4.0", "geoplanet:7.4.1", "geoplanet:7.5.1", "geoplanet:7.5.2", "geoplanet:7.6.0", "geoplanet:7.8.1", "geoplanet:7.9.0", "geoplanet:7.10.0", "geoplanet:8.0.0", "woeplanet:8.0.0"], "meta:indexed": "2020-08-20T20:56:29.445031", "meta:updated": "2020-10-14T12:06:59.252471", "woe:hierarchy": {"continent": 24865671, "country": 23424936, "town": 0, "planet": 1, "county": 12598917, "suburb": 0, "state": 2346916, "region": 0, "localadmin": 0}, "woe:timezone_id": 28350866, "woe:hash": "v34m939yz0bg", "woe:centroid": [59.471699, 51.6012], "geom:latitude": 51.6012, "geom:longitude": 59.471699, "geom:hash": "v34m939yz0bg", "woe:latitude": 51.6012, "geom:centroid": [59.471699, 51.6012], "woe:longitude": 59.471699, "woe:repo": "woeplanet-airport-ru", "geom:area": 0.0, "woe:scale": 19}}