{"type": "Feature", "id": 12516228, "geometry": {"type": "Point", "coordinates": [88.622803, 49.946098]}, "properties": {"woe:id": 12516228, "woe:parent_id": 2121540, "woe:name": "Kosh Agach Airport", "woe:placetype": 14, "woe:placetype_name": "Airport", "woe:lang": "ENG", "iso:country": "RU", "meta:provider": ["geoplanet:7.3.1", "geoplanet:7.3.2", "geoplanet:7.4.0", "geoplanet:7.4.1", "geoplanet:7.5.1", "geoplanet:7.5.2", "geoplanet:7.6.0", "geoplanet:7.8.1", "geoplanet:7.9.0", "geoplanet:7.10.0", "geoplanet:8.0.0", "woeplanet:8.0.0"], "meta:indexed": "2020-08-20T20:56:28.785031", "meta:updated": "2020-10-14T12:06:59.672587", "woe:hierarchy": {"continent": 24865671, "country": 23424936, "town": 0, "planet": 1, "county": 12597676, "suburb": 0, "state": 20070530, "region": 0, "localadmin": 0}, "woe:timezone_id": 56043607, "woe:hash": "vbzh0smjhgrr", "woe:centroid": [88.622803, 49.946098], "geom:latitude": 49.946098, "geom:longitude": 88.622803, "geom:hash": "vbzh0smjhgrr", "woe:latitude": 49.946098, "geom:centroid": [88.622803, 49.946098], "woe:longitude": 88.622803, "woe:repo": "woeplanet-airport-ru", "geom:area": 0.0, "woe:scale": 19}}