{"type": "Feature", "id": 12516742, "properties": {"woe:id": 12516742, "woe:parent_id": 2071441, "woe:name": "Prochnookopskaya Northeast Airport", "woe:placetype": 14, "woe:placetype_name": "Airport", "woe:lang": "ENG", "iso:country": "RU", "meta:provider": ["geoplanet:7.3.1", "geoplanet:7.3.2", "geoplanet:7.4.0", "geoplanet:7.4.1", "geoplanet:7.5.1", "geoplanet:7.5.2", "geoplanet:7.6.0", "geoplanet:7.8.1", "geoplanet:7.9.0", "geoplanet:7.10.0", "geoplanet:8.0.0", "woeplanet:8.0.0"], "meta:indexed": "2020-08-20T20:56:29.237609", "meta:updated": "2020-08-22T02:53:12.208014", "woe:hierarchy": {"continent": 24865671, "country": 23424936, "town": 0, "planet": 1, "county": 12597798, "suburb": 0, "state": 2346884, "region": 0, "localadmin": 0}, "woe:timezone_id": 56043614, "woe:hash": "ubj0rxnvyepf", "woe:centroid": [41.120399, 45.083401], "geom:latitude": 45.083401, "geom:longitude": 41.120399, "geom:hash": "ubj0rxnvyepf", "woe:latitude": 45.083401, "geom:centroid": [41.120399, 45.083401], "woe:longitude": 41.120399, "woe:repo": "woeplanet-airport-ru"}, "geometry": {"coordinates": [41.120399, 45.083401], "type": "Point"}}