{"type": "Feature", "id": 12516239, "properties": {"woe:id": 12516239, "woe:parent_id": 2108948, "woe:name": "Kotly Airport", "woe:placetype": 14, "woe:placetype_name": "Airport", "woe:lang": "ENG", "iso:country": "RU", "meta:provider": ["geoplanet:7.3.1", "geoplanet:7.3.2", "geoplanet:7.4.0", "geoplanet:7.4.1", "geoplanet:7.5.1", "geoplanet:7.5.2", "geoplanet:7.6.0", "geoplanet:7.8.1", "geoplanet:7.9.0", "geoplanet:7.10.0", "geoplanet:8.0.0", "woeplanet:8.0.0"], "meta:indexed": "2020-08-20T20:56:28.795719", "meta:updated": "2020-08-22T02:53:12.020989", "woe:hierarchy": {"continent": 24865671, "country": 23424936, "town": 0, "planet": 1, "county": 12598639, "suburb": 0, "state": 2346907, "region": 0, "localadmin": 0}, "woe:timezone_id": 56043614, "woe:hash": "uds6zr9wqmt4", "woe:centroid": [28.797501, 59.5882], "geom:latitude": 59.5882, "geom:longitude": 28.797501, "geom:hash": "uds6zr9wqmt4", "woe:latitude": 59.5882, "geom:centroid": [28.797501, 59.5882], "woe:longitude": 28.797501, "woe:repo": "woeplanet-airport-ru"}, "geometry": {"coordinates": [28.797501, 59.5882], "type": "Point"}}