{"type": "Feature", "id": 12516746, "geometry": {"type": "Point", "coordinates": [97.809097, 58.423599]}, "properties": {"woe:id": 12516746, "woe:parent_id": 2028758, "woe:name": "Promposelok East Airport", "woe:placetype": 14, "woe:placetype_name": "Airport", "woe:lang": "ENG", "iso:country": "RU", "meta:provider": ["geoplanet:7.3.1", "geoplanet:7.3.2", "geoplanet:7.4.0", "geoplanet:7.4.1", "geoplanet:7.5.1", "geoplanet:7.5.2", "geoplanet:7.6.0", "geoplanet:7.8.1", "geoplanet:7.9.0", "geoplanet:7.10.0", "geoplanet:8.0.0", "woeplanet:8.0.0"], "meta:indexed": "2020-08-20T20:56:29.240813", "meta:updated": "2020-10-14T12:06:58.962524", "woe:hierarchy": {"continent": 24865671, "country": 23424936, "town": 0, "planet": 1, "county": 12597839, "suburb": 0, "state": 20070524, "region": 0, "localadmin": 0}, "woe:timezone_id": 28350837, "woe:hash": "y4ms3ewqjhhz", "woe:centroid": [97.809097, 58.423599], "geom:latitude": 58.423599, "geom:longitude": 97.809097, "geom:hash": "y4ms3ewqjhhz", "woe:latitude": 58.423599, "geom:centroid": [97.809097, 58.423599], "woe:longitude": 97.809097, "woe:repo": "woeplanet-airport-ru", "geom:area": 0.0, "woe:scale": 19}}