{"type": "Feature", "id": 12516771, "geometry": {"type": "Point", "coordinates": [39.277802, 45.155602]}, "properties": {"woe:id": 12516771, "woe:parent_id": 2001292, "woe:name": "Rechka Kochety Pervaya Airport", "woe:placetype": 14, "woe:placetype_name": "Airport", "woe:lang": "ENG", "iso:country": "RU", "meta:provider": ["geoplanet:7.3.1", "geoplanet:7.3.2", "geoplanet:7.4.0", "geoplanet:7.4.1", "geoplanet:7.5.1", "geoplanet:7.5.2", "geoplanet:7.6.0", "geoplanet:7.8.1", "geoplanet:7.9.0", "geoplanet:7.10.0", "geoplanet:8.0.0", "woeplanet:8.0.0"], "meta:indexed": "2020-08-20T20:56:29.261098", "meta:updated": "2020-10-14T12:06:58.936658", "woe:hierarchy": {"continent": 24865671, "country": 23424936, "town": 0, "planet": 1, "county": 12597774, "suburb": 0, "state": 2346884, "region": 0, "localadmin": 0}, "woe:timezone_id": 56043614, "woe:hash": "ub5bvu34rn7f", "woe:centroid": [39.277802, 45.155602], "geom:latitude": 45.155602, "geom:longitude": 39.277802, "geom:hash": "ub5bvu34rn7f", "woe:latitude": 45.155602, "geom:centroid": [39.277802, 45.155602], "woe:longitude": 39.277802, "woe:repo": "woeplanet-airport-ru", "geom:area": 0.0, "woe:scale": 19}}