{"type": "Feature", "id": 12515758, "properties": {"woe:id": 12515758, "woe:parent_id": 2123331, "woe:name": "Bagay Baranovka Airport", "woe:placetype": 14, "woe:placetype_name": "Airport", "woe:lang": "ENG", "iso:country": "RU", "meta:provider": ["geoplanet:7.3.1", "geoplanet:7.3.2", "geoplanet:7.4.0", "geoplanet:7.4.1", "geoplanet:7.5.1", "geoplanet:7.5.2", "geoplanet:7.6.0", "geoplanet:7.8.1", "geoplanet:7.9.0", "geoplanet:7.10.0", "geoplanet:8.0.0", "woeplanet:8.0.0"], "meta:indexed": "2020-08-20T20:56:28.366449", "meta:updated": "2020-08-22T02:53:11.843875", "woe:hierarchy": {"continent": 24865671, "country": 23424936, "town": 0, "planet": 1, "county": 12599257, "suburb": 0, "state": 2346924, "region": 0, "localadmin": 0}, "woe:timezone_id": 28350866, "woe:hash": "v132s7wn1beg", "woe:centroid": [46.9529, 52.1394], "geom:latitude": 52.1394, "geom:longitude": 46.9529, "geom:hash": "v132s7wn1beg", "woe:latitude": 52.1394, "geom:centroid": [46.9529, 52.1394], "woe:longitude": 46.9529, "woe:repo": "woeplanet-airport-ru"}, "geometry": {"coordinates": [46.9529, 52.1394], "type": "Point"}}