{"type": "Feature", "id": 12516571, "geometry": {"type": "Point", "coordinates": [72.902603, 67.687798]}, "properties": {"woe:id": 12516571, "woe:parent_id": 2057880, "woe:name": "Novyy Port Airport", "woe:placetype": 14, "woe:placetype_name": "Airport", "woe:lang": "ENG", "iso:country": "RU", "meta:provider": ["geoplanet:7.3.1", "geoplanet:7.3.2", "geoplanet:7.4.0", "geoplanet:7.4.1", "geoplanet:7.5.1", "geoplanet:7.5.2", "geoplanet:7.6.0", "geoplanet:7.8.1", "geoplanet:7.9.0", "geoplanet:7.10.0", "geoplanet:8.0.0", "woeplanet:8.0.0"], "meta:indexed": "2020-08-20T20:56:29.097571", "meta:updated": "2020-10-14T12:06:59.538178", "woe:hierarchy": {"continent": 24865671, "country": 23424936, "town": 0, "planet": 1, "county": 12599496, "suburb": 0, "state": 20070525, "region": 0, "localadmin": 0}, "woe:timezone_id": 28350866, "woe:hash": "vs5c4fnn1b0f", "woe:centroid": [72.902603, 67.687798], "geom:latitude": 67.687798, "geom:longitude": 72.902603, "geom:hash": "vs5c4fnn1b0f", "woe:latitude": 67.687798, "geom:centroid": [72.902603, 67.687798], "woe:longitude": 72.902603, "woe:repo": "woeplanet-airport-ru", "geom:area": 0.0, "woe:scale": 19}}