{"type": "Feature", "id": 12517076, "properties": {"woe:id": 12517076, "woe:parent_id": 2018480, "woe:name": "Ulskiy Airport", "woe:placetype": 14, "woe:placetype_name": "Airport", "woe:lang": "ENG", "iso:country": "RU", "meta:provider": ["geoplanet:7.3.1", "geoplanet:7.3.2", "geoplanet:7.4.0", "geoplanet:7.4.1", "geoplanet:7.5.1", "geoplanet:7.5.2", "geoplanet:7.6.0", "geoplanet:7.8.1", "geoplanet:7.9.0", "geoplanet:7.10.0", "geoplanet:8.0.0", "woeplanet:8.0.0"], "meta:indexed": "2020-08-20T20:56:29.518848", "meta:updated": "2020-08-22T02:53:12.335039", "woe:hierarchy": {"continent": 24865671, "country": 23424936, "town": 0, "planet": 1, "county": 12597776, "suburb": 0, "state": 20070520, "region": 0, "localadmin": 0}, "woe:timezone_id": 56043614, "woe:hash": "szuw9fjnkf9z", "woe:centroid": [40.162102, 44.748402], "geom:latitude": 44.748402, "geom:longitude": 40.162102, "geom:hash": "szuw9fjnkf9z", "woe:latitude": 44.748402, "geom:centroid": [40.162102, 44.748402], "woe:longitude": 40.162102, "woe:repo": "woeplanet-airport-ru"}, "geometry": {"coordinates": [40.162102, 44.748402], "type": "Point"}}