{"type": "Feature", "id": 12515980, "geometry": {"type": "Point", "coordinates": [40.654999, 47.9748]}, "properties": {"woe:id": 12515980, "woe:parent_id": 2120951, "woe:name": "Ford Dubovoy Airport", "woe:placetype": 14, "woe:placetype_name": "Airport", "woe:lang": "ENG", "iso:country": "RU", "meta:provider": ["geoplanet:7.3.1", "geoplanet:7.3.2", "geoplanet:7.4.0", "geoplanet:7.4.1", "geoplanet:7.5.1", "geoplanet:7.5.2", "geoplanet:7.6.0", "geoplanet:7.8.1", "geoplanet:7.9.0", "geoplanet:7.10.0", "geoplanet:8.0.0", "woeplanet:8.0.0"], "meta:indexed": "2020-08-20T20:56:28.552266", "meta:updated": "2020-10-14T12:06:58.866363", "woe:hierarchy": {"continent": 24865671, "country": 23424936, "town": 0, "planet": 1, "county": 12599102, "suburb": 0, "state": 2346921, "region": 0, "localadmin": 0}, "woe:timezone_id": 56043614, "woe:hash": "ubsbvjs16num", "woe:centroid": [40.654999, 47.9748], "geom:latitude": 47.9748, "geom:longitude": 40.654999, "geom:hash": "ubsbvjs16num", "woe:latitude": 47.9748, "geom:centroid": [40.654999, 47.9748], "woe:longitude": 40.654999, "woe:repo": "woeplanet-airport-ru", "geom:area": 0.0, "woe:scale": 19}}