{"type": "Feature", "id": 12516002, "properties": {"woe:id": 12516002, "woe:parent_id": 1983255, "woe:name": "Gorelovo Airport", "woe:placetype": 14, "woe:placetype_name": "Airport", "woe:lang": "ENG", "iso:country": "RU", "meta:provider": ["geoplanet:7.3.1", "geoplanet:7.3.2", "geoplanet:7.4.0", "geoplanet:7.4.1", "geoplanet:7.5.1", "geoplanet:7.5.2", "geoplanet:7.6.0", "geoplanet:7.8.1", "geoplanet:7.9.0", "geoplanet:7.10.0", "geoplanet:8.0.0", "woeplanet:8.0.0"], "meta:indexed": "2020-08-20T20:56:28.572937", "meta:updated": "2020-08-22T02:53:11.931503", "woe:hierarchy": {"continent": 24865671, "country": 23424936, "town": 0, "planet": 1, "county": 12598654, "suburb": 0, "state": 20070507, "region": 0, "localadmin": 0}, "woe:timezone_id": 56043614, "woe:hash": "udt7uq9v26tn", "woe:centroid": [30.072001, 59.758301], "geom:latitude": 59.758301, "geom:longitude": 30.072001, "geom:hash": "udt7uq9v26tn", "woe:latitude": 59.758301, "geom:centroid": [30.072001, 59.758301], "woe:longitude": 30.072001, "woe:repo": "woeplanet-airport-ru"}, "geometry": {"coordinates": [30.072001, 59.758301], "type": "Point"}}