{"type": "Feature", "id": 12516749, "geometry": {"type": "Point", "coordinates": [99.3797, 58.581501]}, "properties": {"woe:id": 12516749, "woe:parent_id": 2071868, "woe:name": "Prospikhina Airport", "woe:placetype": 14, "woe:placetype_name": "Airport", "woe:lang": "ENG", "iso:country": "RU", "meta:provider": ["geoplanet:7.3.1", "geoplanet:7.3.2", "geoplanet:7.4.0", "geoplanet:7.4.1", "geoplanet:7.5.1", "geoplanet:7.5.2", "geoplanet:7.6.0", "geoplanet:7.8.1", "geoplanet:7.9.0", "geoplanet:7.10.0", "geoplanet:8.0.0", "woeplanet:8.0.0"], "meta:indexed": "2020-08-20T20:56:29.243155", "meta:updated": "2020-10-14T12:06:58.938154", "woe:hierarchy": {"continent": 24865671, "country": 23424936, "town": 0, "planet": 1, "county": 12597858, "suburb": 0, "state": 20070524, "region": 0, "localadmin": 0}, "woe:timezone_id": 28350837, "woe:hash": "y4qtm2qjfz71", "woe:centroid": [99.3797, 58.581501], "geom:latitude": 58.581501, "geom:longitude": 99.3797, "geom:hash": "y4qtm2qjfz71", "woe:latitude": 58.581501, "geom:centroid": [99.3797, 58.581501], "woe:longitude": 99.3797, "woe:repo": "woeplanet-airport-ru", "geom:area": 0.0, "woe:scale": 19}}