{"type": "Feature", "id": 12516204, "properties": {"woe:id": 12516204, "woe:parent_id": 2024005, "woe:name": "Kolik Yegan Airport", "woe:placetype": 14, "woe:placetype_name": "Airport", "woe:lang": "ENG", "iso:country": "RU", "meta:provider": ["geoplanet:7.3.1", "geoplanet:7.3.2", "geoplanet:7.4.0", "geoplanet:7.4.1", "geoplanet:7.5.1", "geoplanet:7.5.2", "geoplanet:7.6.0", "geoplanet:7.8.1", "geoplanet:7.9.0", "geoplanet:7.10.0", "geoplanet:8.0.0", "woeplanet:8.0.0"], "meta:indexed": "2020-08-20T20:56:28.762804", "meta:updated": "2020-08-22T02:53:12.009472", "woe:hierarchy": {"continent": 24865671, "country": 23424936, "town": 0, "planet": 1, "county": 12599464, "suburb": 0, "state": 20070526, "region": 0, "localadmin": 0}, "woe:timezone_id": 28350866, "woe:hash": "vfbr0w22v5v0", "woe:centroid": [79.1241, 61.7337], "geom:latitude": 61.7337, "geom:longitude": 79.1241, "geom:hash": "vfbr0w22v5v0", "woe:latitude": 61.7337, "geom:centroid": [79.1241, 61.7337], "woe:longitude": 79.1241, "woe:repo": "woeplanet-airport-ru"}, "geometry": {"coordinates": [79.1241, 61.7337], "type": "Point"}}