{"type": "Feature", "id": 12517252, "properties": {"woe:id": 12517252, "woe:parent_id": 2101841, "woe:name": "Yemal Stan Southwest Airport", "woe:placetype": 14, "woe:placetype_name": "Airport", "woe:lang": "ENG", "iso:country": "RU", "meta:provider": ["geoplanet:7.3.1", "geoplanet:7.3.2", "geoplanet:7.4.0", "geoplanet:7.4.1", "geoplanet:7.5.1", "geoplanet:7.5.2", "geoplanet:7.6.0", "geoplanet:7.8.1", "geoplanet:7.9.0", "geoplanet:7.10.0", "geoplanet:8.0.0", "woeplanet:8.0.0"], "meta:indexed": "2020-08-20T20:56:29.662177", "meta:updated": "2020-08-22T02:53:12.396718", "woe:hierarchy": {"continent": 24865671, "country": 23424936, "town": 0, "planet": 1, "county": 12597447, "suburb": 0, "state": 2346874, "region": 0, "localadmin": 0}, "woe:timezone_id": 56043614, "woe:hash": "v4v7gntv95zd", "woe:centroid": [52.522598, 61.1646], "geom:latitude": 61.1646, "geom:longitude": 52.522598, "geom:hash": "v4v7gntv95zd", "woe:latitude": 61.1646, "geom:centroid": [52.522598, 61.1646], "woe:longitude": 52.522598, "woe:repo": "woeplanet-airport-ru"}, "geometry": {"coordinates": [52.522598, 61.1646], "type": "Point"}}