{"type": "Feature", "id": 12516675, "properties": {"woe:id": 12516675, "woe:parent_id": 2064728, "woe:name": "Pervomaysk Airport", "woe:placetype": 14, "woe:placetype_name": "Airport", "woe:lang": "ENG", "iso:country": "RU", "meta:provider": ["geoplanet:7.3.1", "geoplanet:7.3.2", "geoplanet:7.4.0", "geoplanet:7.4.1", "geoplanet:7.5.1", "geoplanet:7.5.2", "geoplanet:7.6.0", "geoplanet:7.8.1", "geoplanet:7.9.0", "geoplanet:7.10.0", "geoplanet:8.0.0", "woeplanet:8.0.0"], "meta:indexed": "2020-08-20T20:56:29.183012", "meta:updated": "2020-08-22T02:53:12.184941", "woe:hierarchy": {"continent": 24865671, "country": 23424936, "town": 0, "planet": 1, "county": 12599205, "suburb": 0, "state": 2346937, "region": 0, "localadmin": 0}, "woe:timezone_id": 56043610, "woe:hash": "z0vuhr3vf666", "woe:centroid": [143.275208, 49.9627], "geom:latitude": 49.9627, "geom:longitude": 143.275208, "geom:hash": "z0vuhr3vf666", "woe:latitude": 49.9627, "geom:centroid": [143.275208, 49.9627], "woe:longitude": 143.275208, "woe:repo": "woeplanet-airport-ru"}, "geometry": {"coordinates": [143.275208, 49.9627], "type": "Point"}}