{"type": "Feature", "id": 12517049, "properties": {"woe:id": 12517049, "woe:parent_id": 2124768, "woe:name": "Tura Airport", "woe:placetype": 14, "woe:placetype_name": "Airport", "woe:lang": "ENG", "iso:country": "RU", "meta:provider": ["geoplanet:7.3.1", "geoplanet:7.3.2", "geoplanet:7.4.0", "geoplanet:7.4.1", "geoplanet:7.5.1", "geoplanet:7.5.2", "geoplanet:7.6.0", "geoplanet:7.8.1", "geoplanet:7.9.0", "geoplanet:7.10.0", "geoplanet:8.0.0", "woeplanet:8.0.0"], "meta:indexed": "2020-08-20T20:56:29.493568", "meta:updated": "2020-08-22T02:53:12.322920", "woe:hierarchy": {"continent": 24865671, "country": 23424936, "town": 0, "planet": 1, "county": 56437940, "suburb": 0, "state": 20070524, "region": 0, "localadmin": 0}, "woe:timezone_id": 28350837, "woe:hash": "y5rm9z3knpnf", "woe:centroid": [100.2742, 64.288597], "geom:latitude": 64.288597, "geom:longitude": 100.2742, "geom:hash": "y5rm9z3knpnf", "woe:latitude": 64.288597, "geom:centroid": [100.2742, 64.288597], "woe:longitude": 100.2742, "woe:repo": "woeplanet-airport-ru"}, "geometry": {"coordinates": [100.2742, 64.288597], "type": "Point"}}