{"type": "Feature", "id": 12515907, "properties": {"woe:id": 12515907, "woe:parent_id": 1998426, "woe:name": "Chernyshevskiy Airport", "woe:placetype": 14, "woe:placetype_name": "Airport", "woe:lang": "ENG", "iso:country": "RU", "meta:provider": ["geoplanet:7.3.1", "geoplanet:7.3.2", "geoplanet:7.4.0", "geoplanet:7.4.1", "geoplanet:7.5.1", "geoplanet:7.5.2", "geoplanet:7.6.0", "geoplanet:7.8.1", "geoplanet:7.9.0", "geoplanet:7.10.0", "geoplanet:8.0.0", "woeplanet:8.0.0"], "meta:indexed": "2020-08-20T20:56:28.485166", "meta:updated": "2020-08-22T02:53:11.896857", "woe:hierarchy": {"continent": 24865671, "country": 23424936, "town": 0, "planet": 1, "county": 12597635, "suburb": 0, "state": 2346881, "region": 0, "localadmin": 0}, "woe:timezone_id": 28350865, "woe:hash": "y7pyw8x142xt", "woe:centroid": [112.443802, 63.0205], "geom:latitude": 63.0205, "geom:longitude": 112.443802, "geom:hash": "y7pyw8x142xt", "woe:latitude": 63.0205, "geom:centroid": [112.443802, 63.0205], "woe:longitude": 112.443802, "woe:repo": "woeplanet-airport-ru"}, "geometry": {"coordinates": [112.443802, 63.0205], "type": "Point"}}