{"type": "Feature", "id": 12516693, "geometry": {"type": "Point", "coordinates": [63.160702, 61.2784]}, "properties": {"woe:id": 12516693, "woe:parent_id": 2114030, "woe:name": "Pionerskiy Airport", "woe:placetype": 14, "woe:placetype_name": "Airport", "woe:lang": "ENG", "iso:country": "RU", "meta:provider": ["geoplanet:7.3.1", "geoplanet:7.3.2", "geoplanet:7.4.0", "geoplanet:7.4.1", "geoplanet:7.5.1", "geoplanet:7.5.2", "geoplanet:7.6.0", "geoplanet:7.8.1", "geoplanet:7.9.0", "geoplanet:7.10.0", "geoplanet:8.0.0", "woeplanet:8.0.0"], "meta:indexed": "2020-08-20T20:56:29.197061", "meta:updated": "2020-10-14T12:06:59.464253", "woe:hierarchy": {"continent": 24865671, "country": 23424936, "town": 0, "planet": 1, "county": 12599481, "suburb": 0, "state": 20070526, "region": 0, "localadmin": 0}, "woe:timezone_id": 28350866, "woe:hash": "v6uut72hx18y", "woe:centroid": [63.160702, 61.2784], "geom:latitude": 61.2784, "geom:longitude": 63.160702, "geom:hash": "v6uut72hx18y", "woe:latitude": 61.2784, "geom:centroid": [63.160702, 61.2784], "woe:longitude": 63.160702, "woe:repo": "woeplanet-airport-ru", "geom:area": 0.0, "woe:scale": 19}}