{"type": "Feature", "id": 12516665, "geometry": {"type": "Point", "coordinates": [57.109501, 65.117897]}, "properties": {"woe:id": 12516665, "woe:parent_id": 2121581, "woe:name": "Pechora Southwest Airport", "woe:placetype": 14, "woe:placetype_name": "Airport", "woe:lang": "ENG", "iso:country": "RU", "meta:provider": ["geoplanet:7.3.1", "geoplanet:7.3.2", "geoplanet:7.4.0", "geoplanet:7.4.1", "geoplanet:7.5.1", "geoplanet:7.5.2", "geoplanet:7.6.0", "geoplanet:7.8.1", "geoplanet:7.9.0", "geoplanet:7.10.0", "geoplanet:8.0.0", "woeplanet:8.0.0"], "meta:indexed": "2020-08-20T20:56:29.174938", "woe:alias_ENG_V": ["PEX Airport", "PEX", "Pechora Southwest"], "meta:updated": "2020-10-14T12:06:59.452203", "woe:hierarchy": {"continent": 24865671, "country": 23424936, "town": 0, "planet": 1, "county": 12597449, "suburb": 0, "state": 2346874, "region": 0, "localadmin": 0}, "woe:timezone_id": 56043614, "woe:hash": "v78d7w3g5zf6", "woe:centroid": [57.109501, 65.117897], "geom:latitude": 65.117897, "geom:longitude": 57.109501, "geom:hash": "v78d7w3g5zf6", "woe:latitude": 65.117897, "geom:centroid": [57.109501, 65.117897], "woe:longitude": 57.109501, "woe:repo": "woeplanet-airport-ru", "geom:area": 0.0, "woe:scale": 19}}