{"type": "Feature", "id": 12515849, "geometry": {"type": "Point", "coordinates": [105.819603, 50.773998]}, "properties": {"woe:id": 12515849, "woe:parent_id": 1987860, "woe:name": "Borgoy Airport", "woe:placetype": 14, "woe:placetype_name": "Airport", "woe:lang": "ENG", "iso:country": "RU", "meta:provider": ["geoplanet:7.3.1", "geoplanet:7.3.2", "geoplanet:7.4.0", "geoplanet:7.4.1", "geoplanet:7.5.1", "geoplanet:7.5.2", "geoplanet:7.6.0", "geoplanet:7.8.1", "geoplanet:7.9.0", "geoplanet:7.10.0", "geoplanet:8.0.0", "woeplanet:8.0.0"], "meta:indexed": "2020-08-20T20:56:28.439389", "meta:updated": "2020-10-14T12:06:59.381152", "woe:hierarchy": {"continent": 24865671, "country": 23424936, "town": 0, "planet": 1, "county": 12597282, "suburb": 0, "state": 2346867, "region": 0, "localadmin": 0}, "woe:timezone_id": 28350829, "woe:hash": "y350zgp7zrnz", "woe:centroid": [105.819603, 50.773998], "geom:latitude": 50.773998, "geom:longitude": 105.819603, "geom:hash": "y350zgp7zrnz", "woe:latitude": 50.773998, "geom:centroid": [105.819603, 50.773998], "woe:longitude": 105.819603, "woe:repo": "woeplanet-airport-ru", "geom:area": 0.0, "woe:scale": 19}}