{"type": "Feature", "id": 12517197, "properties": {"woe:id": 12517197, "woe:parent_id": 1998538, "woe:name": "Voronezh-Chertovitskoye Airport", "woe:placetype": 14, "woe:placetype_name": "Airport", "woe:lang": "ENG", "iso:country": "RU", "meta:provider": ["geoplanet:7.3.1", "geoplanet:7.3.2", "geoplanet:7.4.0", "geoplanet:7.4.1", "geoplanet:7.5.1", "geoplanet:7.5.2", "geoplanet:7.6.0", "geoplanet:7.8.1", "geoplanet:7.9.0", "geoplanet:7.10.0", "geoplanet:8.0.0", "woeplanet:8.0.0"], "meta:indexed": "2020-08-20T20:56:29.619675", "woe:alias_ENG_V": ["VOZ Airport", "VOZ", "Voronezh-Chertovitskoye"], "meta:updated": "2020-08-22T02:53:12.377061", "woe:hierarchy": {"continent": 24865671, "country": 23424936, "town": 0, "planet": 1, "county": 12598685, "suburb": 0, "state": 2346935, "region": 0, "localadmin": 0}, "woe:timezone_id": 56043614, "woe:hash": "uc5ysxd0wnu0", "woe:centroid": [39.224201, 51.808899], "geom:latitude": 51.808899, "geom:longitude": 39.224201, "geom:hash": "uc5ysxd0wnu0", "woe:latitude": 51.808899, "geom:centroid": [39.224201, 51.808899], "woe:longitude": 39.224201, "woe:repo": "woeplanet-airport-ru"}, "geometry": {"coordinates": [39.224201, 51.808899], "type": "Point"}}