{"type": "Feature", "id": 12517237, "properties": {"woe:id": 12517237, "woe:parent_id": 2124447, "woe:name": "Yasenskaya Airport", "woe:placetype": 14, "woe:placetype_name": "Airport", "woe:lang": "ENG", "iso:country": "RU", "meta:provider": ["geoplanet:7.3.1", "geoplanet:7.3.2", "geoplanet:7.4.0", "geoplanet:7.4.1", "geoplanet:7.5.1", "geoplanet:7.5.2", "geoplanet:7.6.0", "geoplanet:7.8.1", "geoplanet:7.9.0", "geoplanet:7.10.0", "geoplanet:8.0.0", "woeplanet:8.0.0"], "meta:indexed": "2020-08-20T20:56:29.650374", "meta:updated": "2020-08-22T02:53:12.392414", "woe:hierarchy": {"continent": 24865671, "country": 23424936, "town": 0, "planet": 1, "county": 12597824, "suburb": 0, "state": 2346884, "region": 0, "localadmin": 0}, "woe:timezone_id": 56043614, "woe:hash": "ub5pyv4c769e", "woe:centroid": [38.269299, 46.389999], "geom:latitude": 46.389999, "geom:longitude": 38.269299, "geom:hash": "ub5pyv4c769e", "woe:latitude": 46.389999, "geom:centroid": [38.269299, 46.389999], "woe:longitude": 38.269299, "woe:repo": "woeplanet-airport-ru"}, "geometry": {"coordinates": [38.269299, 46.389999], "type": "Point"}}