{"type": "Feature", "id": 12515983, "properties": {"woe:id": 12515983, "woe:parent_id": 2006333, "woe:name": "Garmanda Airport", "woe:placetype": 14, "woe:placetype_name": "Airport", "woe:lang": "ENG", "iso:country": "RU", "meta:provider": ["geoplanet:7.3.1", "geoplanet:7.3.2", "geoplanet:7.4.0", "geoplanet:7.4.1", "geoplanet:7.5.1", "geoplanet:7.5.2", "geoplanet:7.6.0", "geoplanet:7.8.1", "geoplanet:7.9.0", "geoplanet:7.10.0", "geoplanet:8.0.0", "woeplanet:8.0.0"], "meta:indexed": "2020-08-20T20:56:28.555103", "meta:updated": "2020-08-22T02:53:11.924568", "woe:hierarchy": {"continent": 24865671, "country": 23424936, "town": 0, "planet": 1, "county": 12598703, "suburb": 0, "state": 20070512, "region": 0, "localadmin": 0}, "woe:timezone_id": 28350841, "woe:hash": "ze11z7ve6hu0", "woe:centroid": [159.232498, 62.2038], "geom:latitude": 62.2038, "geom:longitude": 159.232498, "geom:hash": "ze11z7ve6hu0", "woe:latitude": 62.2038, "geom:centroid": [159.232498, 62.2038], "woe:longitude": 159.232498, "woe:repo": "woeplanet-airport-ru"}, "geometry": {"coordinates": [159.232498, 62.2038], "type": "Point"}}