{"type": "Feature", "id": 12517241, "properties": {"woe:id": 12517241, "woe:parent_id": 1995797, "woe:name": "Yefremov Northeast Airport", "woe:placetype": 14, "woe:placetype_name": "Airport", "woe:lang": "ENG", "iso:country": "RU", "meta:provider": ["geoplanet:7.3.1", "geoplanet:7.3.2", "geoplanet:7.4.0", "geoplanet:7.4.1", "geoplanet:7.5.1", "geoplanet:7.5.2", "geoplanet:7.6.0", "geoplanet:7.8.1", "geoplanet:7.9.0", "geoplanet:7.10.0", "geoplanet:8.0.0", "woeplanet:8.0.0"], "meta:indexed": "2020-08-20T20:56:29.653798", "meta:updated": "2020-08-22T02:53:12.393614", "woe:hierarchy": {"continent": 24865671, "country": 23424936, "town": 0, "planet": 1, "county": 12599435, "suburb": 0, "state": 2346929, "region": 0, "localadmin": 0}, "woe:timezone_id": 56043614, "woe:hash": "uc7nsqum5qkp", "woe:centroid": [38.161499, 53.2118], "geom:latitude": 53.2118, "geom:longitude": 38.161499, "geom:hash": "uc7nsqum5qkp", "woe:latitude": 53.2118, "geom:centroid": [38.161499, 53.2118], "woe:longitude": 38.161499, "woe:repo": "woeplanet-airport-ru"}, "geometry": {"coordinates": [38.161499, 53.2118], "type": "Point"}}