{"type": "Feature", "id": 12517093, "geometry": {"type": "Point", "coordinates": [150.533005, 46.206299]}, "properties": {"woe:id": 12517093, "woe:parent_id": 1982029, "woe:name": "Urup Airport", "woe:placetype": 14, "woe:placetype_name": "Airport", "woe:lang": "ENG", "iso:country": "RU", "meta:provider": ["geoplanet:7.3.1", "geoplanet:7.3.2", "geoplanet:7.4.0", "geoplanet:7.4.1", "geoplanet:7.5.1", "geoplanet:7.5.2", "geoplanet:7.6.0", "geoplanet:7.8.1", "geoplanet:7.9.0", "geoplanet:7.10.0", "geoplanet:8.0.0", "woeplanet:8.0.0"], "meta:indexed": "2020-08-20T20:56:29.535346", "meta:updated": "2020-10-14T12:06:59.338007", "woe:hierarchy": {"continent": 24865671, "country": 23424936, "town": 0, "planet": 1, "county": 12599195, "suburb": 0, "state": 2346937, "region": 0, "localadmin": 0}, "woe:timezone_id": 56043610, "woe:hash": "z25nc7wg1q2j", "woe:centroid": [150.533005, 46.206299], "geom:latitude": 46.206299, "geom:longitude": 150.533005, "geom:hash": "z25nc7wg1q2j", "woe:latitude": 46.206299, "geom:centroid": [150.533005, 46.206299], "woe:longitude": 150.533005, "woe:repo": "woeplanet-airport-ru", "geom:area": 0.0, "woe:scale": 19}}