{"type": "Feature", "id": 12515740, "geometry": {"type": "Point", "coordinates": [124.919502, 63.637199]}, "properties": {"woe:id": 12515740, "woe:parent_id": 2039525, "woe:name": "Aryktakh Airport", "woe:placetype": 14, "woe:placetype_name": "Airport", "woe:lang": "ENG", "iso:country": "RU", "meta:provider": ["geoplanet:7.3.1", "geoplanet:7.3.2", "geoplanet:7.4.0", "geoplanet:7.4.1", "geoplanet:7.5.1", "geoplanet:7.5.2", "geoplanet:7.6.0", "geoplanet:7.8.1", "geoplanet:7.9.0", "geoplanet:7.10.0", "geoplanet:8.0.0", "woeplanet:8.0.0"], "meta:indexed": "2020-08-20T20:56:28.351611", "meta:updated": "2020-10-14T12:06:59.175340", "woe:hierarchy": {"continent": 24865671, "country": 23424936, "town": 0, "planet": 1, "county": 12597631, "suburb": 0, "state": 2346881, "region": 0, "localadmin": 0}, "woe:timezone_id": 28350865, "woe:hash": "yg2f48g9e3ey", "woe:centroid": [124.919502, 63.637199], "geom:latitude": 63.637199, "geom:longitude": 124.919502, "geom:hash": "yg2f48g9e3ey", "woe:latitude": 63.637199, "geom:centroid": [124.919502, 63.637199], "woe:longitude": 124.919502, "woe:repo": "woeplanet-airport-ru", "geom:area": 0.0, "woe:scale": 19}}