{"type": "Feature", "id": 12515926, "geometry": {"type": "Point", "coordinates": [49.7668, 54.822899]}, "properties": {"woe:id": 12515926, "woe:parent_id": 1999801, "woe:name": "Chuyashskoye Shapkino Airport", "woe:placetype": 14, "woe:placetype_name": "Airport", "woe:lang": "ENG", "iso:country": "RU", "meta:provider": ["geoplanet:7.3.1", "geoplanet:7.3.2", "geoplanet:7.4.0", "geoplanet:7.4.1", "geoplanet:7.5.1", "geoplanet:7.5.2", "geoplanet:7.6.0", "geoplanet:7.8.1", "geoplanet:7.9.0", "geoplanet:7.10.0", "geoplanet:8.0.0", "woeplanet:8.0.0"], "meta:indexed": "2020-08-20T20:56:28.501938", "meta:updated": "2020-10-14T12:06:58.886583", "woe:hierarchy": {"continent": 24865671, "country": 23424936, "town": 0, "planet": 1, "county": 12597521, "suburb": 0, "state": 2346878, "region": 0, "localadmin": 0}, "woe:timezone_id": 56043614, "woe:hash": "v1erukpnd3pd", "woe:centroid": [49.7668, 54.822899], "geom:latitude": 54.822899, "geom:longitude": 49.7668, "geom:hash": "v1erukpnd3pd", "woe:latitude": 54.822899, "geom:centroid": [49.7668, 54.822899], "woe:longitude": 49.7668, "woe:repo": "woeplanet-airport-ru", "geom:area": 0.0, "woe:scale": 19}}