{"type": "Feature", "id": 12516310, "properties": {"woe:id": 12516310, "woe:parent_id": 2121791, "woe:name": "Kurumkan Airport", "woe:placetype": 14, "woe:placetype_name": "Airport", "woe:lang": "ENG", "iso:country": "RU", "meta:provider": ["geoplanet:7.3.1", "geoplanet:7.3.2", "geoplanet:7.4.0", "geoplanet:7.4.1", "geoplanet:7.5.1", "geoplanet:7.5.2", "geoplanet:7.6.0", "geoplanet:7.8.1", "geoplanet:7.9.0", "geoplanet:7.10.0", "geoplanet:8.0.0", "woeplanet:8.0.0"], "meta:indexed": "2020-08-20T20:56:28.863071", "meta:updated": "2020-08-22T02:53:12.048310", "woe:hierarchy": {"continent": 24865671, "country": 23424936, "town": 0, "planet": 1, "county": 12597288, "suburb": 0, "state": 2346867, "region": 0, "localadmin": 0}, "woe:timezone_id": 28350829, "woe:hash": "y3wkyp4u405c", "woe:centroid": [110.306602, 54.3116], "geom:latitude": 54.3116, "geom:longitude": 110.306602, "geom:hash": "y3wkyp4u405c", "woe:latitude": 54.3116, "geom:centroid": [110.306602, 54.3116], "woe:longitude": 110.306602, "woe:repo": "woeplanet-airport-ru"}, "geometry": {"coordinates": [110.306602, 54.3116], "type": "Point"}}