{"type": "Feature", "id": 12516409, "properties": {"woe:id": 12516409, "woe:parent_id": 1981732, "woe:name": "Maryanovka Airport", "woe:placetype": 14, "woe:placetype_name": "Airport", "woe:lang": "ENG", "iso:country": "RU", "meta:provider": ["geoplanet:7.3.1", "geoplanet:7.3.2", "geoplanet:7.4.0", "geoplanet:7.4.1", "geoplanet:7.5.1", "geoplanet:7.5.2", "geoplanet:7.6.0", "geoplanet:7.8.1", "geoplanet:7.9.0", "geoplanet:7.10.0", "geoplanet:8.0.0", "woeplanet:8.0.0"], "meta:indexed": "2020-08-20T20:56:28.954397", "meta:updated": "2020-08-22T02:53:12.083859", "woe:hierarchy": {"continent": 24865671, "country": 23424936, "town": 0, "planet": 1, "county": 12598890, "suburb": 0, "state": 2346915, "region": 0, "localadmin": 0}, "woe:timezone_id": 56043608, "woe:hash": "v9g8tyc7zqrp", "woe:centroid": [72.676598, 54.969398], "geom:latitude": 54.969398, "geom:longitude": 72.676598, "geom:hash": "v9g8tyc7zqrp", "woe:latitude": 54.969398, "geom:centroid": [72.676598, 54.969398], "woe:longitude": 72.676598, "woe:repo": "woeplanet-airport-ru"}, "geometry": {"coordinates": [72.676598, 54.969398], "type": "Point"}}