{"type": "Feature", "id": 12516686, "geometry": {"type": "Point", "coordinates": [108.888199, 51.314301]}, "properties": {"woe:id": 12516686, "woe:parent_id": 2065754, "woe:name": "Petrovsk Zavaykalskiy Airport", "woe:placetype": 14, "woe:placetype_name": "Airport", "woe:lang": "ENG", "iso:country": "RU", "meta:provider": ["geoplanet:7.3.1", "geoplanet:7.3.2", "geoplanet:7.4.0", "geoplanet:7.4.1", "geoplanet:7.5.1", "geoplanet:7.5.2", "geoplanet:7.6.0", "geoplanet:7.8.1", "geoplanet:7.9.0", "geoplanet:7.10.0", "geoplanet:8.0.0", "woeplanet:8.0.0"], "meta:indexed": "2020-08-20T20:56:29.191832", "meta:updated": "2020-10-14T12:06:59.412723", "woe:hierarchy": {"continent": 24865671, "country": 23424936, "town": 0, "planet": 1, "county": 12598183, "suburb": 0, "state": 56437930, "region": 0, "localadmin": 0}, "woe:timezone_id": 28350865, "woe:hash": "y3j7vv3zqzjb", "woe:centroid": [108.888199, 51.314301], "geom:latitude": 51.314301, "geom:longitude": 108.888199, "geom:hash": "y3j7vv3zqzjb", "woe:latitude": 51.314301, "geom:centroid": [108.888199, 51.314301], "woe:longitude": 108.888199, "woe:repo": "woeplanet-airport-ru", "geom:area": 0.0, "woe:scale": 19}}