{"type": "Feature", "id": 12516558, "properties": {"woe:id": 12516558, "woe:parent_id": 2049280, "woe:name": "Novorossiysk Airport", "woe:placetype": 14, "woe:placetype_name": "Airport", "woe:lang": "ENG", "iso:country": "RU", "meta:provider": ["geoplanet:7.3.1", "geoplanet:7.3.2", "geoplanet:7.4.0", "geoplanet:7.4.1", "geoplanet:7.5.1", "geoplanet:7.5.2", "geoplanet:7.6.0", "geoplanet:7.8.1", "geoplanet:7.9.0", "geoplanet:7.10.0", "geoplanet:8.0.0", "woeplanet:8.0.0"], "meta:indexed": "2020-08-20T20:56:29.086750", "meta:updated": "2020-08-22T02:53:12.140251", "woe:hierarchy": {"continent": 24865671, "country": 23424936, "town": 0, "planet": 1, "county": 12597799, "suburb": 0, "state": 2346884, "region": 0, "localadmin": 0}, "woe:timezone_id": 56043614, "woe:hash": "szfy5exbc3t7", "woe:centroid": [37.7817, 44.667801], "geom:latitude": 44.667801, "geom:longitude": 37.7817, "geom:hash": "szfy5exbc3t7", "woe:latitude": 44.667801, "geom:centroid": [37.7817, 44.667801], "woe:longitude": 37.7817, "woe:repo": "woeplanet-airport-ru"}, "geometry": {"coordinates": [37.7817, 44.667801], "type": "Point"}}