{"type": "Feature", "id": 12516114, "geometry": {"type": "Point", "coordinates": [40.4394, 45.348801]}, "properties": {"woe:id": 12516114, "woe:parent_id": 2031570, "woe:name": "Kazanskaya Airport", "woe:placetype": 14, "woe:placetype_name": "Airport", "woe:lang": "ENG", "iso:country": "RU", "meta:provider": ["geoplanet:7.3.1", "geoplanet:7.3.2", "geoplanet:7.4.0", "geoplanet:7.4.1", "geoplanet:7.5.1", "geoplanet:7.5.2", "geoplanet:7.6.0", "geoplanet:7.8.1", "geoplanet:7.9.0", "geoplanet:7.10.0", "geoplanet:8.0.0", "woeplanet:8.0.0"], "meta:indexed": "2020-08-20T20:56:28.677375", "meta:updated": "2020-10-14T12:06:59.139506", "woe:hierarchy": {"continent": 24865671, "country": 23424936, "town": 0, "planet": 1, "county": 12597778, "suburb": 0, "state": 2346884, "region": 0, "localadmin": 0}, "woe:timezone_id": 56043614, "woe:hash": "ubhcbprpfm4p", "woe:centroid": [40.4394, 45.348801], "geom:latitude": 45.348801, "geom:longitude": 40.4394, "geom:hash": "ubhcbprpfm4p", "woe:latitude": 45.348801, "geom:centroid": [40.4394, 45.348801], "woe:longitude": 40.4394, "woe:repo": "woeplanet-airport-ru", "geom:area": 0.0, "woe:scale": 19}}