{"type": "Feature", "id": 12517085, "geometry": {"type": "Point", "coordinates": [111.637604, 56.133499]}, "properties": {"woe:id": 12517085, "woe:parent_id": 2100428, "woe:name": "Uoyan Airport", "woe:placetype": 14, "woe:placetype_name": "Airport", "woe:lang": "ENG", "iso:country": "RU", "meta:provider": ["geoplanet:7.3.1", "geoplanet:7.3.2", "geoplanet:7.4.0", "geoplanet:7.4.1", "geoplanet:7.5.1", "geoplanet:7.5.2", "geoplanet:7.6.0", "geoplanet:7.8.1", "geoplanet:7.9.0", "geoplanet:7.10.0", "geoplanet:8.0.0", "woeplanet:8.0.0"], "meta:indexed": "2020-08-20T20:56:29.527807", "meta:updated": "2020-10-14T12:06:59.345656", "woe:hierarchy": {"continent": 24865671, "country": 23424936, "town": 0, "planet": 1, "county": 12597295, "suburb": 0, "state": 2346867, "region": 0, "localadmin": 0}, "woe:timezone_id": 28350829, "woe:hash": "y3zrk6u12dwu", "woe:centroid": [111.637604, 56.133499], "geom:latitude": 56.133499, "geom:longitude": 111.637604, "geom:hash": "y3zrk6u12dwu", "woe:latitude": 56.133499, "geom:centroid": [111.637604, 56.133499], "woe:longitude": 111.637604, "woe:repo": "woeplanet-airport-ru", "geom:area": 0.0, "woe:scale": 19}}