{"type": "Feature", "id": 12516614, "properties": {"woe:id": 12516614, "woe:parent_id": 2124280, "woe:name": "Ordzhonikidze West Airport", "woe:placetype": 14, "woe:placetype_name": "Airport", "woe:lang": "ENG", "iso:country": "RU", "meta:provider": ["geoplanet:7.3.1", "geoplanet:7.3.2", "geoplanet:7.4.0", "geoplanet:7.4.1", "geoplanet:7.5.1", "geoplanet:7.5.2", "geoplanet:7.6.0", "geoplanet:7.8.1", "geoplanet:7.9.0", "geoplanet:7.10.0", "geoplanet:8.0.0", "woeplanet:8.0.0"], "meta:indexed": "2020-08-20T20:56:29.132803", "meta:updated": "2020-08-22T02:53:12.162110", "woe:hierarchy": {"continent": 24865671, "country": 23424936, "town": 0, "planet": 1, "county": 12597517, "suburb": 0, "state": 2346877, "region": 0, "localadmin": 0}, "woe:timezone_id": 56043614, "woe:hash": "szxsz7sz4645", "woe:centroid": [44.622101, 43.0429], "geom:latitude": 43.0429, "geom:longitude": 44.622101, "geom:hash": "szxsz7sz4645", "woe:latitude": 43.0429, "geom:centroid": [44.622101, 43.0429], "woe:longitude": 44.622101, "woe:repo": "woeplanet-airport-ru"}, "geometry": {"coordinates": [44.622101, 43.0429], "type": "Point"}}