{"type": "Feature", "id": 12515772, "properties": {"woe:id": 12515772, "woe:parent_id": 2050552, "woe:name": "Bambuyko Airport", "woe:placetype": 14, "woe:placetype_name": "Airport", "woe:lang": "ENG", "iso:country": "RU", "meta:provider": ["geoplanet:7.3.1", "geoplanet:7.3.2", "geoplanet:7.4.0", "geoplanet:7.4.1", "geoplanet:7.5.1", "geoplanet:7.5.2", "geoplanet:7.6.0", "geoplanet:7.8.1", "geoplanet:7.9.0", "geoplanet:7.10.0", "geoplanet:8.0.0", "woeplanet:8.0.0"], "meta:indexed": "2020-08-20T20:56:28.377551", "meta:updated": "2020-08-22T02:53:11.848229", "woe:hierarchy": {"continent": 24865671, "country": 23424936, "town": 0, "planet": 1, "county": 12597291, "suburb": 0, "state": 2346867, "region": 0, "localadmin": 0}, "woe:timezone_id": 28350865, "woe:hash": "y9fm7jcdvxnq", "woe:centroid": [115.798203, 55.798698], "geom:latitude": 55.798698, "geom:longitude": 115.798203, "geom:hash": "y9fm7jcdvxnq", "woe:latitude": 55.798698, "geom:centroid": [115.798203, 55.798698], "woe:longitude": 115.798203, "woe:repo": "woeplanet-airport-ru"}, "geometry": {"coordinates": [115.798203, 55.798698], "type": "Point"}}