{"type": "Feature", "id": 12516419, "geometry": {"type": "Point", "coordinates": [76.108597, 61.025299]}, "properties": {"woe:id": 12516419, "woe:parent_id": 2122153, "woe:name": "Megion Airport", "woe:placetype": 14, "woe:placetype_name": "Airport", "woe:lang": "ENG", "iso:country": "RU", "meta:provider": ["geoplanet:7.3.1", "geoplanet:7.3.2", "geoplanet:7.4.0", "geoplanet:7.4.1", "geoplanet:7.5.1", "geoplanet:7.5.2", "geoplanet:7.6.0", "geoplanet:7.8.1", "geoplanet:7.9.0", "geoplanet:7.10.0", "geoplanet:8.0.0", "woeplanet:8.0.0"], "meta:indexed": "2020-08-20T20:56:28.963965", "meta:updated": "2020-10-14T12:06:59.768371", "woe:hierarchy": {"continent": 24865671, "country": 23424936, "town": 0, "planet": 1, "county": 12599464, "suburb": 0, "state": 20070526, "region": 0, "localadmin": 0}, "woe:timezone_id": 28350866, "woe:hash": "vdy55vkd4u70", "woe:centroid": [76.108597, 61.025299], "geom:latitude": 61.025299, "geom:longitude": 76.108597, "geom:hash": "vdy55vkd4u70", "woe:latitude": 61.025299, "geom:centroid": [76.108597, 61.025299], "woe:longitude": 76.108597, "woe:repo": "woeplanet-airport-ru", "geom:area": 0.0, "woe:scale": 19}}