{"type": "Feature", "id": 12515991, "geometry": {"type": "Point", "coordinates": [39.9599, 44.8871]}, "properties": {"woe:id": 12515991, "woe:parent_id": 2042499, "woe:name": "Giaginskaya Northwest Airport", "woe:placetype": 14, "woe:placetype_name": "Airport", "woe:lang": "ENG", "iso:country": "RU", "meta:provider": ["geoplanet:7.3.1", "geoplanet:7.3.2", "geoplanet:7.4.0", "geoplanet:7.4.1", "geoplanet:7.5.1", "geoplanet:7.5.2", "geoplanet:7.6.0", "geoplanet:7.8.1", "geoplanet:7.9.0", "geoplanet:7.10.0", "geoplanet:8.0.0", "woeplanet:8.0.0"], "meta:indexed": "2020-08-20T20:56:28.562633", "meta:updated": "2020-10-14T12:06:58.857641", "woe:hierarchy": {"continent": 24865671, "country": 23424936, "town": 0, "planet": 1, "county": 12597776, "suburb": 0, "state": 20070520, "region": 0, "localadmin": 0}, "woe:timezone_id": 56043614, "woe:hash": "szurm73ym1vj", "woe:centroid": [39.9599, 44.8871], "geom:latitude": 44.8871, "geom:longitude": 39.9599, "geom:hash": "szurm73ym1vj", "woe:latitude": 44.8871, "geom:centroid": [39.9599, 44.8871], "woe:longitude": 39.9599, "woe:repo": "woeplanet-airport-ru", "geom:area": 0.0, "woe:scale": 19}}