{"type": "Feature", "id": 12516392, "properties": {"woe:id": 12516392, "woe:parent_id": 2041314, "woe:name": "Malovskiy Airport", "woe:placetype": 14, "woe:placetype_name": "Airport", "woe:lang": "ENG", "iso:country": "RU", "meta:provider": ["geoplanet:7.3.1", "geoplanet:7.3.2", "geoplanet:7.4.0", "geoplanet:7.4.1", "geoplanet:7.5.1", "geoplanet:7.5.2", "geoplanet:7.6.0", "geoplanet:7.8.1", "geoplanet:7.9.0", "geoplanet:7.10.0", "geoplanet:8.0.0", "woeplanet:8.0.0"], "meta:indexed": "2020-08-20T20:56:28.938599", "meta:updated": "2020-08-22T02:53:12.077958", "woe:hierarchy": {"continent": 24865671, "country": 23424936, "town": 0, "planet": 1, "county": 12598160, "suburb": 0, "state": 2346867, "region": 0, "localadmin": 0}, "woe:timezone_id": 28350829, "woe:hash": "y98tq67ps87w", "woe:centroid": [113.482101, 54.374001], "geom:latitude": 54.374001, "geom:longitude": 113.482101, "geom:hash": "y98tq67ps87w", "woe:latitude": 54.374001, "geom:centroid": [113.482101, 54.374001], "woe:longitude": 113.482101, "woe:repo": "woeplanet-airport-ru"}, "geometry": {"coordinates": [113.482101, 54.374001], "type": "Point"}}