{"type": "Feature", "id": 12517043, "geometry": {"type": "Point", "coordinates": [100.492996, 54.584301]}, "properties": {"woe:id": 12517043, "woe:parent_id": 2027170, "woe:name": "Tulun Northwest Airport", "woe:placetype": 14, "woe:placetype_name": "Airport", "woe:lang": "ENG", "iso:country": "RU", "meta:provider": ["geoplanet:7.3.1", "geoplanet:7.3.2", "geoplanet:7.4.0", "geoplanet:7.4.1", "geoplanet:7.5.1", "geoplanet:7.5.2", "geoplanet:7.6.0", "geoplanet:7.8.1", "geoplanet:7.9.0", "geoplanet:7.10.0", "geoplanet:8.0.0", "woeplanet:8.0.0"], "meta:indexed": "2020-08-20T20:56:29.487906", "meta:updated": "2020-10-14T12:06:59.344906", "woe:hierarchy": {"continent": 24865671, "country": 23424936, "town": 0, "planet": 1, "county": 12598283, "suburb": 0, "state": 2346896, "region": 0, "localadmin": 0}, "woe:timezone_id": 28350829, "woe:hash": "y1xqwbbb8e0y", "woe:centroid": [100.492996, 54.584301], "geom:latitude": 54.584301, "geom:longitude": 100.492996, "geom:hash": "y1xqwbbb8e0y", "woe:latitude": 54.584301, "geom:centroid": [100.492996, 54.584301], "woe:longitude": 100.492996, "woe:repo": "woeplanet-airport-ru", "geom:area": 0.0, "woe:scale": 19}}