{"type": "Feature", "id": 12516887, "geometry": {"type": "Point", "coordinates": [50.370098, 53.2365]}, "properties": {"woe:id": 12516887, "woe:parent_id": 12598631, "woe:name": "Smyshlayevka Airport", "woe:placetype": 14, "woe:placetype_name": "Airport", "woe:lang": "ENG", "iso:country": "RU", "meta:provider": ["geoplanet:7.3.1", "geoplanet:7.3.2", "geoplanet:7.4.0", "geoplanet:7.4.1", "geoplanet:7.5.1", "geoplanet:7.5.2", "geoplanet:7.6.0", "geoplanet:7.8.1", "geoplanet:7.9.0", "geoplanet:7.10.0", "geoplanet:8.0.0", "woeplanet:8.0.0"], "meta:indexed": "2020-08-20T20:56:29.354488", "meta:updated": "2020-10-14T12:06:59.836357", "woe:hierarchy": {"continent": 24865671, "country": 23424936, "town": 0, "planet": 1, "county": 12598631, "suburb": 0, "state": 2346906, "region": 0, "localadmin": 0}, "woe:timezone_id": 28350915, "woe:hash": "v17yf5qmh6gk", "woe:centroid": [50.370098, 53.2365], "geom:latitude": 53.2365, "geom:longitude": 50.370098, "geom:hash": "v17yf5qmh6gk", "woe:latitude": 53.2365, "geom:centroid": [50.370098, 53.2365], "woe:longitude": 50.370098, "woe:repo": "woeplanet-airport-ru", "geom:area": 0.0, "woe:scale": 19}}