{"type": "Feature", "id": 12517068, "geometry": {"type": "Point", "coordinates": [55.87442, 54.55751]}, "properties": {"woe:id": 12517068, "woe:parent_id": 2097312, "woe:name": "Ufa South Airport", "woe:placetype": 14, "woe:placetype_name": "Airport", "woe:lang": "ENG", "iso:country": "RU", "meta:provider": ["geoplanet:7.3.1", "geoplanet:7.3.2", "geoplanet:7.4.0", "geoplanet:7.4.1", "geoplanet:7.5.1", "geoplanet:7.5.2", "geoplanet:7.6.0", "geoplanet:7.8.1", "geoplanet:7.9.0", "geoplanet:7.10.0", "geoplanet:8.0.0", "woeplanet:8.0.0"], "meta:indexed": "2020-08-20T20:56:29.721235", "woe:alias_ENG_V": ["UFA", "UFA Airport", "Ufa South"], "meta:updated": "2020-10-14T12:06:59.325750", "woe:hierarchy": {"continent": 24865671, "country": 23424936, "town": 0, "planet": 1, "county": 12597274, "suburb": 0, "state": 2346866, "region": 0, "localadmin": 0}, "woe:timezone_id": 28350866, "woe:hash": "v1xwr7ys82gr", "woe:centroid": [55.87442, 54.55751], "geom:latitude": 54.55751, "geom:longitude": 55.87442, "geom:hash": "v1xwr7ys82gr", "woe:latitude": 54.55751, "geom:centroid": [55.87442, 54.55751], "woe:longitude": 55.87442, "woe:repo": "woeplanet-airport-ru", "geom:area": 0.0, "woe:scale": 19}}