{"type": "Feature", "id": 12516276, "properties": {"woe:id": 12516276, "woe:parent_id": 2030124, "woe:name": "Krasnyye Tkachi Airport", "woe:placetype": 14, "woe:placetype_name": "Airport", "woe:lang": "ENG", "iso:country": "RU", "meta:provider": ["geoplanet:7.3.1", "geoplanet:7.3.2", "geoplanet:7.4.0", "geoplanet:7.4.1", "geoplanet:7.5.1", "geoplanet:7.5.2", "geoplanet:7.6.0", "geoplanet:7.8.1", "geoplanet:7.9.0", "geoplanet:7.10.0", "geoplanet:8.0.0", "woeplanet:8.0.0"], "meta:indexed": "2020-08-20T20:56:28.830651", "meta:updated": "2020-08-22T02:53:12.035268", "woe:hierarchy": {"continent": 24865671, "country": 23424936, "town": 0, "planet": 1, "county": 12599680, "suburb": 0, "state": 2346936, "region": 0, "localadmin": 0}, "woe:timezone_id": 56043614, "woe:hash": "ufhqfhfm1kfr", "woe:centroid": [39.8176, 57.463501], "geom:latitude": 57.463501, "geom:longitude": 39.8176, "geom:hash": "ufhqfhfm1kfr", "woe:latitude": 57.463501, "geom:centroid": [39.8176, 57.463501], "woe:longitude": 39.8176, "woe:repo": "woeplanet-airport-ru"}, "geometry": {"coordinates": [39.8176, 57.463501], "type": "Point"}}