{"type": "Feature", "id": 12516785, "geometry": {"type": "Point", "coordinates": [39.492001, 50.195801]}, "properties": {"woe:id": 12516785, "woe:parent_id": 2067487, "woe:name": "Rossosh West Airport", "woe:placetype": 14, "woe:placetype_name": "Airport", "woe:lang": "ENG", "iso:country": "RU", "meta:provider": ["geoplanet:7.3.1", "geoplanet:7.3.2", "geoplanet:7.4.0", "geoplanet:7.4.1", "geoplanet:7.5.1", "geoplanet:7.5.2", "geoplanet:7.6.0", "geoplanet:7.8.1", "geoplanet:7.9.0", "geoplanet:7.10.0", "geoplanet:8.0.0", "woeplanet:8.0.0"], "meta:indexed": "2020-08-20T20:56:29.273066", "meta:updated": "2020-10-14T12:06:58.965060", "woe:hierarchy": {"continent": 24865671, "country": 23424936, "town": 0, "planet": 1, "county": 12599650, "suburb": 0, "state": 2346935, "region": 0, "localadmin": 0}, "woe:timezone_id": 56043614, "woe:hash": "ubujd9v5wrd2", "woe:centroid": [39.492001, 50.195801], "geom:latitude": 50.195801, "geom:longitude": 39.492001, "geom:hash": "ubujd9v5wrd2", "woe:latitude": 50.195801, "geom:centroid": [39.492001, 50.195801], "woe:longitude": 39.492001, "woe:repo": "woeplanet-airport-ru", "geom:area": 0.0, "woe:scale": 19}}