{"type": "Feature", "id": 12516026, "geometry": {"type": "Point", "coordinates": [102.492996, 71.975098]}, "properties": {"woe:id": 12516026, "woe:parent_id": 2019316, "woe:name": "Hatanga Airport", "woe:placetype": 14, "woe:placetype_name": "Airport", "woe:lang": "ENG", "iso:country": "RU", "meta:provider": ["geoplanet:7.3.1", "geoplanet:7.3.2", "geoplanet:7.4.0", "geoplanet:7.4.1", "geoplanet:7.5.1", "geoplanet:7.5.2", "geoplanet:7.6.0", "geoplanet:7.8.1", "geoplanet:7.9.0", "geoplanet:7.10.0", "geoplanet:8.0.0", "woeplanet:8.0.0"], "meta:indexed": "2020-08-20T20:56:28.595306", "woe:alias_ENG_V": ["HTG Airport", "HTG"], "meta:updated": "2020-10-14T12:06:59.086300", "woe:hierarchy": {"continent": 24865671, "country": 23424936, "town": 0, "planet": 1, "county": 12597859, "suburb": 0, "state": 20070524, "region": 0, "localadmin": 0}, "woe:timezone_id": 28350837, "woe:hash": "ykbckq9j7fsz", "woe:centroid": [102.492996, 71.975098], "geom:latitude": 71.975098, "geom:longitude": 102.492996, "geom:hash": "ykbckq9j7fsz", "woe:latitude": 71.975098, "geom:centroid": [102.492996, 71.975098], "woe:longitude": 102.492996, "woe:repo": "woeplanet-airport-ru", "geom:area": 0.0, "woe:scale": 19}}