{"type": "Feature", "id": 12516417, "properties": {"woe:id": 12516417, "woe:parent_id": 2044467, "woe:name": "Medvedevo Airport", "woe:placetype": 14, "woe:placetype_name": "Airport", "woe:lang": "ENG", "iso:country": "RU", "meta:provider": ["geoplanet:7.3.1", "geoplanet:7.3.2", "geoplanet:7.4.0", "geoplanet:7.4.1", "geoplanet:7.5.1", "geoplanet:7.5.2", "geoplanet:7.6.0", "geoplanet:7.8.1", "geoplanet:7.9.0", "geoplanet:7.10.0", "geoplanet:8.0.0", "woeplanet:8.0.0"], "meta:indexed": "2020-08-20T20:56:28.962024", "meta:updated": "2020-08-22T02:53:12.086279", "woe:hierarchy": {"continent": 24865671, "country": 23424936, "town": 0, "planet": 1, "county": 12599609, "suburb": 0, "state": 2346934, "region": 0, "localadmin": 0}, "woe:timezone_id": 56043613, "woe:hash": "ufwt7x62wqsx", "woe:centroid": [43.047798, 60.025299], "geom:latitude": 60.025299, "geom:longitude": 43.047798, "geom:hash": "ufwt7x62wqsx", "woe:latitude": 60.025299, "geom:centroid": [43.047798, 60.025299], "woe:longitude": 43.047798, "woe:repo": "woeplanet-airport-ru"}, "geometry": {"coordinates": [43.047798, 60.025299], "type": "Point"}}