{"type": "Feature", "id": 12517240, "geometry": {"type": "Point", "coordinates": [127.996002, 53.303398]}, "properties": {"woe:id": 12517240, "woe:parent_id": 2111784, "woe:name": "Yasnyy Airport", "woe:placetype": 14, "woe:placetype_name": "Airport", "woe:lang": "ENG", "iso:country": "RU", "meta:provider": ["geoplanet:7.3.1", "geoplanet:7.3.2", "geoplanet:7.4.0", "geoplanet:7.4.1", "geoplanet:7.5.1", "geoplanet:7.5.2", "geoplanet:7.6.0", "geoplanet:7.8.1", "geoplanet:7.9.0", "geoplanet:7.10.0", "geoplanet:8.0.0", "woeplanet:8.0.0"], "meta:indexed": "2020-08-20T20:56:29.652940", "meta:updated": "2020-10-14T12:06:59.584775", "woe:hierarchy": {"continent": 24865671, "country": 23424936, "town": 0, "planet": 1, "county": 12598008, "suburb": 0, "state": 2346888, "region": 0, "localadmin": 0}, "woe:timezone_id": 28350865, "woe:hash": "yc7p0xefg18d", "woe:centroid": [127.996002, 53.303398], "geom:latitude": 53.303398, "geom:longitude": 127.996002, "geom:hash": "yc7p0xefg18d", "woe:latitude": 53.303398, "geom:centroid": [127.996002, 53.303398], "woe:longitude": 127.996002, "woe:repo": "woeplanet-airport-ru", "geom:area": 0.0, "woe:scale": 19}}