{"type": "Feature", "id": 12516657, "geometry": {"type": "Point", "coordinates": [40.511299, 52.013901]}, "properties": {"woe:id": 12516657, "woe:parent_id": 2062964, "woe:name": "Parsh Novka Airport", "woe:placetype": 14, "woe:placetype_name": "Airport", "woe:lang": "ENG", "iso:country": "RU", "meta:provider": ["geoplanet:7.3.1", "geoplanet:7.3.2", "geoplanet:7.4.0", "geoplanet:7.4.1", "geoplanet:7.5.1", "geoplanet:7.5.2", "geoplanet:7.6.0", "geoplanet:7.8.1", "geoplanet:7.9.0", "geoplanet:7.10.0", "geoplanet:8.0.0", "woeplanet:8.0.0"], "meta:indexed": "2020-08-20T20:56:29.168314", "meta:updated": "2020-10-14T12:06:59.453341", "woe:hierarchy": {"continent": 24865671, "country": 23424936, "town": 0, "planet": 1, "county": 12598672, "suburb": 0, "state": 2346908, "region": 0, "localadmin": 0}, "woe:timezone_id": 56043614, "woe:hash": "uchzcug6vtvv", "woe:centroid": [40.511299, 52.013901], "geom:latitude": 52.013901, "geom:longitude": 40.511299, "geom:hash": "uchzcug6vtvv", "woe:latitude": 52.013901, "geom:centroid": [40.511299, 52.013901], "woe:longitude": 40.511299, "woe:repo": "woeplanet-airport-ru", "geom:area": 0.0, "woe:scale": 19}}