{"type": "Feature", "id": 12515778, "properties": {"woe:id": 12515778, "woe:parent_id": 2008036, "woe:name": "Barnaui West Airport", "woe:placetype": 14, "woe:placetype_name": "Airport", "woe:lang": "ENG", "iso:country": "RU", "meta:provider": ["geoplanet:7.3.1", "geoplanet:7.3.2", "geoplanet:7.4.0", "geoplanet:7.4.1", "geoplanet:7.5.1", "geoplanet:7.5.2", "geoplanet:7.6.0", "geoplanet:7.8.1", "geoplanet:7.9.0", "geoplanet:7.10.0", "geoplanet:8.0.0", "woeplanet:8.0.0"], "meta:indexed": "2020-08-20T20:56:28.382527", "woe:alias_UNK_V": ["Barnaul"], "woe:alias_ENG_V": ["BAX Airport", "BAX", "Barnaui West"], "meta:updated": "2020-08-22T02:53:11.850089", "woe:alias_UNK_Q": ["Barnaul"], "woe:hierarchy": {"continent": 24865671, "country": 23424936, "town": 0, "planet": 1, "county": 12597660, "suburb": 0, "state": 20070529, "region": 0, "localadmin": 0}, "woe:timezone_id": 56043607, "woe:hash": "vc7rt1yk7quh", "woe:centroid": [83.548767, 53.359989], "geom:latitude": 53.359989, "geom:longitude": 83.548767, "geom:hash": "vc7rt1yk7quh", "woe:latitude": 53.359989, "geom:centroid": [83.548767, 53.359989], "woe:longitude": 83.548767, "woe:repo": "woeplanet-airport-ru"}, "geometry": {"coordinates": [83.548767, 53.359989], "type": "Point"}}