{"type": "Feature", "id": 12516442, "geometry": {"type": "Point", "coordinates": [90.888397, 58.178902]}, "properties": {"woe:id": 12516442, "woe:parent_id": 2040522, "woe:name": "Mokovskoye Airport", "woe:placetype": 14, "woe:placetype_name": "Airport", "woe:lang": "ENG", "iso:country": "RU", "meta:provider": ["geoplanet:7.3.1", "geoplanet:7.3.2", "geoplanet:7.4.0", "geoplanet:7.4.1", "geoplanet:7.5.1", "geoplanet:7.5.2", "geoplanet:7.6.0", "geoplanet:7.8.1", "geoplanet:7.9.0", "geoplanet:7.10.0", "geoplanet:8.0.0", "woeplanet:8.0.0"], "meta:indexed": "2020-08-20T20:56:28.985099", "meta:updated": "2020-10-14T12:06:59.767811", "woe:hierarchy": {"continent": 24865671, "country": 23424936, "town": 0, "planet": 1, "county": 12597896, "suburb": 0, "state": 20070524, "region": 0, "localadmin": 0}, "woe:timezone_id": 28350837, "woe:hash": "y42dupnutjku", "woe:centroid": [90.888397, 58.178902], "geom:latitude": 58.178902, "geom:longitude": 90.888397, "geom:hash": "y42dupnutjku", "woe:latitude": 58.178902, "geom:centroid": [90.888397, 58.178902], "woe:longitude": 90.888397, "woe:repo": "woeplanet-airport-ru", "geom:area": 0.0, "woe:scale": 19}}