{"type": "Feature", "id": 12517025, "geometry": {"type": "Point", "coordinates": [61.673401, 54.111198]}, "properties": {"woe:id": 12517025, "woe:parent_id": 1990197, "woe:name": "Troitsk East Airport", "woe:placetype": 14, "woe:placetype_name": "Airport", "woe:lang": "ENG", "iso:country": "RU", "meta:provider": ["geoplanet:7.3.1", "geoplanet:7.3.2", "geoplanet:7.4.0", "geoplanet:7.4.1", "geoplanet:7.5.1", "geoplanet:7.5.2", "geoplanet:7.6.0", "geoplanet:7.8.1", "geoplanet:7.9.0", "geoplanet:7.10.0", "geoplanet:8.0.0", "woeplanet:8.0.0"], "meta:indexed": "2020-08-20T20:56:29.470831", "meta:updated": "2020-10-14T12:06:59.292461", "woe:hierarchy": {"continent": 24865671, "country": 23424936, "town": 0, "planet": 1, "county": 12598143, "suburb": 0, "state": 2346893, "region": 0, "localadmin": 0}, "woe:timezone_id": 28350866, "woe:hash": "v3egg6thw6kv", "woe:centroid": [61.673401, 54.111198], "geom:latitude": 54.111198, "geom:longitude": 61.673401, "geom:hash": "v3egg6thw6kv", "woe:latitude": 54.111198, "geom:centroid": [61.673401, 54.111198], "woe:longitude": 61.673401, "woe:repo": "woeplanet-airport-ru", "geom:area": 0.0, "woe:scale": 19}}