{"type": "Feature", "id": 12516084, "geometry": {"type": "Point", "coordinates": [125.992897, 57.615101]}, "properties": {"woe:id": 12516084, "woe:parent_id": 2121185, "woe:name": "Kankunskiy Airport", "woe:placetype": 14, "woe:placetype_name": "Airport", "woe:lang": "ENG", "iso:country": "RU", "meta:provider": ["geoplanet:7.3.1", "geoplanet:7.3.2", "geoplanet:7.4.0", "geoplanet:7.4.1", "geoplanet:7.5.1", "geoplanet:7.5.2", "geoplanet:7.6.0", "geoplanet:7.8.1", "geoplanet:7.9.0", "geoplanet:7.10.0", "geoplanet:8.0.0", "woeplanet:8.0.0"], "meta:indexed": "2020-08-20T20:56:28.649947", "meta:updated": "2020-10-14T12:06:59.045856", "woe:hierarchy": {"continent": 24865671, "country": 23424936, "town": 0, "planet": 1, "county": 12597622, "suburb": 0, "state": 2346881, "region": 0, "localadmin": 0}, "woe:timezone_id": 28350865, "woe:hash": "yf1xg090r330", "woe:centroid": [125.992897, 57.615101], "geom:latitude": 57.615101, "geom:longitude": 125.992897, "geom:hash": "yf1xg090r330", "woe:latitude": 57.615101, "geom:centroid": [125.992897, 57.615101], "woe:longitude": 125.992897, "woe:repo": "woeplanet-airport-ru", "geom:area": 0.0, "woe:scale": 19}}