{"type": "Feature", "id": 12516413, "geometry": {"type": "Point", "coordinates": [132.417007, 43.428501]}, "properties": {"woe:id": 12516413, "woe:parent_id": 2083708, "woe:name": "Maykhe Airport", "woe:placetype": 14, "woe:placetype_name": "Airport", "woe:lang": "ENG", "iso:country": "RU", "meta:provider": ["geoplanet:7.3.1", "geoplanet:7.3.2", "geoplanet:7.4.0", "geoplanet:7.4.1", "geoplanet:7.5.1", "geoplanet:7.5.2", "geoplanet:7.6.0", "geoplanet:7.8.1", "geoplanet:7.9.0", "geoplanet:7.10.0", "geoplanet:8.0.0", "woeplanet:8.0.0"], "meta:indexed": "2020-08-20T20:56:28.958177", "meta:updated": "2020-10-14T12:06:59.812403", "woe:hierarchy": {"continent": 24865671, "country": 23424936, "town": 0, "planet": 1, "county": 12597927, "suburb": 0, "state": 2346886, "region": 0, "localadmin": 0}, "woe:timezone_id": 56043609, "woe:hash": "wzwpj1zj7gkg", "woe:centroid": [132.417007, 43.428501], "geom:latitude": 43.428501, "geom:longitude": 132.417007, "geom:hash": "wzwpj1zj7gkg", "woe:latitude": 43.428501, "geom:centroid": [132.417007, 43.428501], "woe:longitude": 132.417007, "woe:repo": "woeplanet-airport-ru", "geom:area": 0.0, "woe:scale": 19}}