{"type": "Feature", "id": 12516057, "properties": {"woe:id": 12516057, "woe:parent_id": 2121031, "woe:name": "Kachalovka Airport", "woe:placetype": 14, "woe:placetype_name": "Airport", "woe:lang": "ENG", "iso:country": "RU", "meta:provider": ["geoplanet:7.3.1", "geoplanet:7.3.2", "geoplanet:7.4.0", "geoplanet:7.4.1", "geoplanet:7.5.1", "geoplanet:7.5.2", "geoplanet:7.6.0", "geoplanet:7.8.1", "geoplanet:7.9.0", "geoplanet:7.10.0", "geoplanet:8.0.0", "woeplanet:8.0.0"], "meta:indexed": "2020-08-20T20:56:28.624470", "meta:updated": "2020-08-22T02:53:11.951429", "woe:hierarchy": {"continent": 24865671, "country": 23424936, "town": 0, "planet": 1, "county": 12598805, "suburb": 0, "state": 2346912, "region": 0, "localadmin": 0}, "woe:timezone_id": 56043614, "woe:hash": "uuh6f0jswv7j", "woe:centroid": [39.8223, 67.9842], "geom:latitude": 67.9842, "geom:longitude": 39.8223, "geom:hash": "uuh6f0jswv7j", "woe:latitude": 67.9842, "geom:centroid": [39.8223, 67.9842], "woe:longitude": 39.8223, "woe:repo": "woeplanet-airport-ru"}, "geometry": {"coordinates": [39.8223, 67.9842], "type": "Point"}}