{"type": "Feature", "id": 12516714, "properties": {"woe:id": 12516714, "woe:parent_id": 1987371, "woe:name": "Polivanov Airport", "woe:placetype": 14, "woe:placetype_name": "Airport", "woe:lang": "ENG", "iso:country": "RU", "meta:provider": ["geoplanet:7.3.1", "geoplanet:7.3.2", "geoplanet:7.4.0", "geoplanet:7.4.1", "geoplanet:7.5.1", "geoplanet:7.5.2", "geoplanet:7.6.0", "geoplanet:7.8.1", "geoplanet:7.9.0", "geoplanet:7.10.0", "geoplanet:8.0.0", "woeplanet:8.0.0"], "meta:indexed": "2020-08-20T20:56:29.214313", "meta:updated": "2020-08-22T02:53:12.199135", "woe:hierarchy": {"continent": 24865671, "country": 23424936, "town": 0, "planet": 1, "county": 12599130, "suburb": 0, "state": 2346921, "region": 0, "localadmin": 0}, "woe:timezone_id": 56043614, "woe:hash": "ubmf81hr4bvb", "woe:centroid": [41.8419, 46.852402], "geom:latitude": 46.852402, "geom:longitude": 41.8419, "geom:hash": "ubmf81hr4bvb", "woe:latitude": 46.852402, "geom:centroid": [41.8419, 46.852402], "woe:longitude": 41.8419, "woe:repo": "woeplanet-airport-ru"}, "geometry": {"coordinates": [41.8419, 46.852402], "type": "Point"}}