{"type": "Feature", "id": 12516012, "geometry": {"type": "Point", "coordinates": [38.630299, 45.649899]}, "properties": {"woe:id": 12516012, "woe:parent_id": 2009703, "woe:name": "Grechanaya Balka Se Airport", "woe:placetype": 14, "woe:placetype_name": "Airport", "woe:lang": "ENG", "iso:country": "RU", "meta:provider": ["geoplanet:7.3.1", "geoplanet:7.3.2", "geoplanet:7.4.0", "geoplanet:7.4.1", "geoplanet:7.5.1", "geoplanet:7.5.2", "geoplanet:7.6.0", "geoplanet:7.8.1", "geoplanet:7.9.0", "geoplanet:7.10.0", "geoplanet:8.0.0", "woeplanet:8.0.0"], "meta:indexed": "2020-08-20T20:56:28.582292", "meta:updated": "2020-10-14T12:06:59.075065", "woe:hierarchy": {"continent": 24865671, "country": 23424936, "town": 0, "planet": 1, "county": 12597779, "suburb": 0, "state": 2346884, "region": 0, "localadmin": 0}, "woe:timezone_id": 56043614, "woe:hash": "ub57xn39zjyw", "woe:centroid": [38.630299, 45.649899], "geom:latitude": 45.649899, "geom:longitude": 38.630299, "geom:hash": "ub57xn39zjyw", "woe:latitude": 45.649899, "geom:centroid": [38.630299, 45.649899], "woe:longitude": 38.630299, "woe:repo": "woeplanet-airport-ru", "geom:area": 0.0, "woe:scale": 19}}