{"type": "Feature", "id": 12517242, "geometry": {"type": "Point", "coordinates": [40.583, 46.5807]}, "properties": {"woe:id": 12517242, "woe:parent_id": 2065788, "woe:name": "Yegorlykskaya West Airport", "woe:placetype": 14, "woe:placetype_name": "Airport", "woe:lang": "ENG", "iso:country": "RU", "meta:provider": ["geoplanet:7.3.1", "geoplanet:7.3.2", "geoplanet:7.4.0", "geoplanet:7.4.1", "geoplanet:7.5.1", "geoplanet:7.5.2", "geoplanet:7.6.0", "geoplanet:7.8.1", "geoplanet:7.9.0", "geoplanet:7.10.0", "geoplanet:8.0.0", "woeplanet:8.0.0"], "meta:indexed": "2020-08-20T20:56:29.654646", "meta:updated": "2020-10-14T12:06:59.575523", "woe:hierarchy": {"continent": 24865671, "country": 23424936, "town": 0, "planet": 1, "county": 12599152, "suburb": 0, "state": 2346921, "region": 0, "localadmin": 0}, "woe:timezone_id": 56043614, "woe:hash": "ubkbgrz8hry4", "woe:centroid": [40.583, 46.5807], "geom:latitude": 46.5807, "geom:longitude": 40.583, "geom:hash": "ubkbgrz8hry4", "woe:latitude": 46.5807, "geom:centroid": [40.583, 46.5807], "woe:longitude": 40.583, "woe:repo": "woeplanet-airport-ru", "geom:area": 0.0, "woe:scale": 19}}