{"type": "Feature", "id": 12515807, "properties": {"woe:id": 12515807, "woe:parent_id": 2120291, "woe:name": "Bestuzhevo Airport", "woe:placetype": 14, "woe:placetype_name": "Airport", "woe:lang": "ENG", "iso:country": "RU", "meta:provider": ["geoplanet:7.3.1", "geoplanet:7.3.2", "geoplanet:7.4.0", "geoplanet:7.4.1", "geoplanet:7.5.1", "geoplanet:7.5.2", "geoplanet:7.6.0", "geoplanet:7.8.1", "geoplanet:7.9.0", "geoplanet:7.10.0", "geoplanet:8.0.0", "woeplanet:8.0.0"], "meta:indexed": "2020-08-20T20:56:28.406088", "meta:updated": "2020-08-22T02:53:11.861502", "woe:hierarchy": {"continent": 24865671, "country": 23424936, "town": 0, "planet": 1, "county": 12599611, "suburb": 0, "state": 20070508, "region": 0, "localadmin": 0}, "woe:timezone_id": 56043614, "woe:hash": "ufzq2hs1nufs", "woe:centroid": [43.951099, 61.5923], "geom:latitude": 61.5923, "geom:longitude": 43.951099, "geom:hash": "ufzq2hs1nufs", "woe:latitude": 61.5923, "geom:centroid": [43.951099, 61.5923], "woe:longitude": 43.951099, "woe:repo": "woeplanet-airport-ru"}, "geometry": {"coordinates": [43.951099, 61.5923], "type": "Point"}}