{"type": "Feature", "id": 12516052, "geometry": {"type": "Point", "coordinates": [53.188599, 56.757301]}, "properties": {"woe:id": 12516052, "woe:parent_id": 2066359, "woe:name": "Izhevsk South Airport", "woe:placetype": 14, "woe:placetype_name": "Airport", "woe:lang": "ENG", "iso:country": "RU", "meta:provider": ["geoplanet:7.3.1", "geoplanet:7.3.2", "geoplanet:7.4.0", "geoplanet:7.4.1", "geoplanet:7.5.1", "geoplanet:7.5.2", "geoplanet:7.6.0", "geoplanet:7.8.1", "geoplanet:7.9.0", "geoplanet:7.10.0", "geoplanet:8.0.0", "woeplanet:8.0.0"], "meta:indexed": "2020-08-20T20:56:28.619768", "meta:updated": "2020-10-14T12:06:59.047338", "woe:hierarchy": {"continent": 24865671, "country": 23424936, "town": 0, "planet": 1, "county": 12597598, "suburb": 0, "state": 2346880, "region": 0, "localadmin": 0}, "woe:timezone_id": 28350866, "woe:hash": "v4jffk6g0pvb", "woe:centroid": [53.188599, 56.757301], "geom:latitude": 56.757301, "geom:longitude": 53.188599, "geom:hash": "v4jffk6g0pvb", "woe:latitude": 56.757301, "geom:centroid": [53.188599, 56.757301], "woe:longitude": 53.188599, "woe:repo": "woeplanet-airport-ru", "geom:area": 0.0, "woe:scale": 19}}