{"type": "Feature", "id": 12516318, "geometry": {"type": "Point", "coordinates": [40.3013, 44.682899]}, "properties": {"woe:id": 12516318, "woe:parent_id": 2121818, "woe:name": "Kuzhorskaya Airport", "woe:placetype": 14, "woe:placetype_name": "Airport", "woe:lang": "ENG", "iso:country": "RU", "meta:provider": ["geoplanet:7.3.1", "geoplanet:7.3.2", "geoplanet:7.4.0", "geoplanet:7.4.1", "geoplanet:7.5.1", "geoplanet:7.5.2", "geoplanet:7.6.0", "geoplanet:7.8.1", "geoplanet:7.9.0", "geoplanet:7.10.0", "geoplanet:8.0.0", "woeplanet:8.0.0"], "meta:indexed": "2020-08-20T20:56:28.869652", "meta:updated": "2020-10-14T12:06:59.700029", "woe:hierarchy": {"continent": 24865671, "country": 23424936, "town": 0, "planet": 1, "county": 12597796, "suburb": 0, "state": 20070520, "region": 0, "localadmin": 0}, "woe:timezone_id": 56043614, "woe:hash": "szuwjn68b256", "woe:centroid": [40.3013, 44.682899], "geom:latitude": 44.682899, "geom:longitude": 40.3013, "geom:hash": "szuwjn68b256", "woe:latitude": 44.682899, "geom:centroid": [40.3013, 44.682899], "woe:longitude": 40.3013, "woe:repo": "woeplanet-airport-ru", "geom:area": 0.0, "woe:scale": 19}}