{"type": "Feature", "id": 12516654, "properties": {"woe:id": 12516654, "woe:parent_id": 2062521, "woe:name": "Pangody Airport", "woe:placetype": 14, "woe:placetype_name": "Airport", "woe:lang": "ENG", "iso:country": "RU", "meta:provider": ["geoplanet:7.3.1", "geoplanet:7.3.2", "geoplanet:7.4.0", "geoplanet:7.4.1", "geoplanet:7.5.1", "geoplanet:7.5.2", "geoplanet:7.6.0", "geoplanet:7.8.1", "geoplanet:7.9.0", "geoplanet:7.10.0", "geoplanet:8.0.0", "woeplanet:8.0.0"], "meta:indexed": "2020-08-20T20:56:29.165982", "meta:updated": "2020-08-22T02:53:12.175848", "woe:hierarchy": {"continent": 24865671, "country": 23424936, "town": 0, "planet": 1, "county": 12599460, "suburb": 0, "state": 20070525, "region": 0, "localadmin": 0}, "woe:timezone_id": 28350866, "woe:hash": "vesyxm5wph7c", "woe:centroid": [74.503403, 65.858597], "geom:latitude": 65.858597, "geom:longitude": 74.503403, "geom:hash": "vesyxm5wph7c", "woe:latitude": 65.858597, "geom:centroid": [74.503403, 65.858597], "woe:longitude": 74.503403, "woe:repo": "woeplanet-airport-ru"}, "geometry": {"coordinates": [74.503403, 65.858597], "type": "Point"}}