{"type": "Feature", "id": 12516070, "properties": {"woe:id": 12516070, "woe:parent_id": 2024516, "woe:name": "Kamarov Airport", "woe:placetype": 14, "woe:placetype_name": "Airport", "woe:lang": "ENG", "iso:country": "RU", "meta:provider": ["geoplanet:7.3.1", "geoplanet:7.3.2", "geoplanet:7.4.0", "geoplanet:7.4.1", "geoplanet:7.5.1", "geoplanet:7.5.2", "geoplanet:7.6.0", "geoplanet:7.8.1", "geoplanet:7.9.0", "geoplanet:7.10.0", "geoplanet:8.0.0", "woeplanet:8.0.0"], "meta:indexed": "2020-08-20T20:56:28.636739", "meta:updated": "2020-08-22T02:53:11.956749", "woe:hierarchy": {"continent": 24865671, "country": 23424936, "town": 0, "planet": 1, "county": 12599117, "suburb": 0, "state": 2346921, "region": 0, "localadmin": 0}, "woe:timezone_id": 56043614, "woe:hash": "ubmm48jc7j2y", "woe:centroid": [41.250702, 47.2854], "geom:latitude": 47.2854, "geom:longitude": 41.250702, "geom:hash": "ubmm48jc7j2y", "woe:latitude": 47.2854, "geom:centroid": [41.250702, 47.2854], "woe:longitude": 41.250702, "woe:repo": "woeplanet-airport-ru"}, "geometry": {"coordinates": [41.250702, 47.2854], "type": "Point"}}