{"type": "Feature", "id": 12516497, "properties": {"woe:id": 12516497, "woe:parent_id": 2051942, "woe:name": "Nikolayersk Airport", "woe:placetype": 14, "woe:placetype_name": "Airport", "woe:lang": "ENG", "iso:country": "RU", "meta:provider": ["geoplanet:7.3.1", "geoplanet:7.3.2", "geoplanet:7.4.0", "geoplanet:7.4.1", "geoplanet:7.5.1", "geoplanet:7.5.2", "geoplanet:7.6.0", "geoplanet:7.8.1", "geoplanet:7.9.0", "geoplanet:7.10.0", "geoplanet:8.0.0", "woeplanet:8.0.0"], "meta:indexed": "2020-08-20T20:56:29.036595", "meta:updated": "2020-08-22T02:53:12.116303", "woe:hierarchy": {"continent": 24865671, "country": 23424936, "town": 0, "planet": 1, "county": 12597750, "suburb": 0, "state": 2346883, "region": 0, "localadmin": 0}, "woe:timezone_id": 56043609, "woe:hash": "z1kn262xbtn6", "woe:centroid": [140.636703, 53.1436], "geom:latitude": 53.1436, "geom:longitude": 140.636703, "geom:hash": "z1kn262xbtn6", "woe:latitude": 53.1436, "geom:centroid": [140.636703, 53.1436], "woe:longitude": 140.636703, "woe:repo": "woeplanet-airport-ru"}, "geometry": {"coordinates": [140.636703, 53.1436], "type": "Point"}}