{"type": "Feature", "id": 12515833, "geometry": {"type": "Point", "coordinates": [52.100601, 56.6129]}, "properties": {"woe:id": 12515833, "woe:parent_id": 1991489, "woe:name": "Bol Shaya Ucha Airport", "woe:placetype": 14, "woe:placetype_name": "Airport", "woe:lang": "ENG", "iso:country": "RU", "meta:provider": ["geoplanet:7.3.1", "geoplanet:7.3.2", "geoplanet:7.4.0", "geoplanet:7.4.1", "geoplanet:7.5.1", "geoplanet:7.5.2", "geoplanet:7.6.0", "geoplanet:7.8.1", "geoplanet:7.9.0", "geoplanet:7.10.0", "geoplanet:8.0.0", "woeplanet:8.0.0"], "meta:indexed": "2020-08-20T20:56:28.427315", "meta:updated": "2020-10-14T12:06:59.394845", "woe:hierarchy": {"continent": 24865671, "country": 23424936, "town": 0, "planet": 1, "county": 12597607, "suburb": 0, "state": 2346880, "region": 0, "localadmin": 0}, "woe:timezone_id": 28350866, "woe:hash": "v4j41d46pcry", "woe:centroid": [52.100601, 56.6129], "geom:latitude": 56.6129, "geom:longitude": 52.100601, "geom:hash": "v4j41d46pcry", "woe:latitude": 56.6129, "geom:centroid": [52.100601, 56.6129], "woe:longitude": 52.100601, "woe:repo": "woeplanet-airport-ru", "geom:area": 0.0, "woe:scale": 19}}