{"type": "Feature", "id": 12515863, "properties": {"woe:id": 12515863, "woe:parent_id": 2126046, "woe:name": "Bryusterort Airport", "woe:placetype": 14, "woe:placetype_name": "Airport", "woe:lang": "ENG", "iso:country": "RU", "meta:provider": ["geoplanet:7.3.1", "geoplanet:7.3.2", "geoplanet:7.4.0", "geoplanet:7.4.1", "geoplanet:7.5.1", "geoplanet:7.5.2", "geoplanet:7.6.0", "geoplanet:7.8.1", "geoplanet:7.9.0", "geoplanet:7.10.0", "geoplanet:8.0.0", "woeplanet:8.0.0"], "meta:indexed": "2020-08-20T20:56:28.450414", "meta:updated": "2020-08-22T02:53:11.880738", "woe:hierarchy": {"continent": 24865671, "country": 23424936, "town": 0, "planet": 1, "county": 12598343, "suburb": 0, "state": 2346938, "region": 0, "localadmin": 0}, "woe:timezone_id": 28350900, "woe:hash": "u3y0w9xp0gx9", "woe:centroid": [19.9828, 54.941101], "geom:latitude": 54.941101, "geom:longitude": 19.9828, "geom:hash": "u3y0w9xp0gx9", "woe:latitude": 54.941101, "geom:centroid": [19.9828, 54.941101], "woe:longitude": 19.9828, "woe:repo": "woeplanet-airport-ru"}, "geometry": {"coordinates": [19.9828, 54.941101], "type": "Point"}}