{"type": "Feature", "id": 12516522, "geometry": {"type": "Point", "coordinates": [143.126205, 51.7994]}, "properties": {"woe:id": 12516522, "woe:parent_id": 2122451, "woe:name": "Nogliki Airport", "woe:placetype": 14, "woe:placetype_name": "Airport", "woe:lang": "ENG", "iso:country": "RU", "meta:provider": ["geoplanet:7.3.1", "geoplanet:7.3.2", "geoplanet:7.4.0", "geoplanet:7.4.1", "geoplanet:7.5.1", "geoplanet:7.5.2", "geoplanet:7.6.0", "geoplanet:7.8.1", "geoplanet:7.9.0", "geoplanet:7.10.0", "geoplanet:8.0.0", "woeplanet:8.0.0"], "meta:indexed": "2020-08-20T20:56:29.058178", "meta:updated": "2020-10-14T12:06:59.523099", "woe:hierarchy": {"continent": 24865671, "country": 23424936, "town": 0, "planet": 1, "county": 12599199, "suburb": 0, "state": 2346937, "region": 0, "localadmin": 0}, "woe:timezone_id": 56043610, "woe:hash": "z1jy8vv36k18", "woe:centroid": [143.126205, 51.7994], "geom:latitude": 51.7994, "geom:longitude": 143.126205, "geom:hash": "z1jy8vv36k18", "woe:latitude": 51.7994, "geom:centroid": [143.126205, 51.7994], "woe:longitude": 143.126205, "woe:repo": "woeplanet-airport-ru", "geom:area": 0.0, "woe:scale": 19}}