{"type": "Feature", "id": 12515941, "geometry": {"type": "Point", "coordinates": [34.619202, 54.416698]}, "properties": {"woe:id": 12515941, "woe:parent_id": 2001635, "woe:name": "Dobraya Airport", "woe:placetype": 14, "woe:placetype_name": "Airport", "woe:lang": "ENG", "iso:country": "RU", "meta:provider": ["geoplanet:7.3.1", "geoplanet:7.3.2", "geoplanet:7.4.0", "geoplanet:7.4.1", "geoplanet:7.5.1", "geoplanet:7.5.2", "geoplanet:7.6.0", "geoplanet:7.8.1", "geoplanet:7.9.0", "geoplanet:7.10.0", "geoplanet:8.0.0", "woeplanet:8.0.0"], "meta:indexed": "2020-08-20T20:56:28.516329", "meta:updated": "2020-10-14T12:06:58.851249", "woe:hierarchy": {"continent": 24865671, "country": 23424936, "town": 0, "planet": 1, "county": 12599261, "suburb": 0, "state": 2346899, "region": 0, "localadmin": 0}, "woe:timezone_id": 56043614, "woe:hash": "uc8tef2bjzez", "woe:centroid": [34.619202, 54.416698], "geom:latitude": 54.416698, "geom:longitude": 34.619202, "geom:hash": "uc8tef2bjzez", "woe:latitude": 54.416698, "geom:centroid": [34.619202, 54.416698], "woe:longitude": 34.619202, "woe:repo": "woeplanet-airport-ru", "geom:area": 0.0, "woe:scale": 19}}