{"type": "Feature", "id": 12516388, "geometry": {"type": "Point", "coordinates": [86.711998, 58.632301]}, "properties": {"woe:id": 12516388, "woe:parent_id": 2090512, "woe:name": "Maksimkin Yar Southwest Airport", "woe:placetype": 14, "woe:placetype_name": "Airport", "woe:lang": "ENG", "iso:country": "RU", "meta:provider": ["geoplanet:7.3.1", "geoplanet:7.3.2", "geoplanet:7.4.0", "geoplanet:7.4.1", "geoplanet:7.5.1", "geoplanet:7.5.2", "geoplanet:7.6.0", "geoplanet:7.8.1", "geoplanet:7.9.0", "geoplanet:7.10.0", "geoplanet:8.0.0", "woeplanet:8.0.0"], "meta:indexed": "2020-08-20T20:56:28.934743", "meta:updated": "2020-10-14T12:06:59.705808", "woe:hierarchy": {"continent": 24865671, "country": 23424936, "town": 0, "planet": 1, "county": 12599404, "suburb": 0, "state": 2346928, "region": 0, "localadmin": 0}, "woe:timezone_id": 28350837, "woe:hash": "vfmtt1tvbj05", "woe:centroid": [86.711998, 58.632301], "geom:latitude": 58.632301, "geom:longitude": 86.711998, "geom:hash": "vfmtt1tvbj05", "woe:latitude": 58.632301, "geom:centroid": [86.711998, 58.632301], "woe:longitude": 86.711998, "woe:repo": "woeplanet-airport-ru", "geom:area": 0.0, "woe:scale": 19}}