{"type": "Feature", "id": 12515852, "geometry": {"type": "Point", "coordinates": [55.729099, 64.882797]}, "properties": {"woe:id": 12515852, "woe:parent_id": 2121107, "woe:name": "Borovaya Southeast Airport", "woe:placetype": 14, "woe:placetype_name": "Airport", "woe:lang": "ENG", "iso:country": "RU", "meta:provider": ["geoplanet:7.3.1", "geoplanet:7.3.2", "geoplanet:7.4.0", "geoplanet:7.4.1", "geoplanet:7.5.1", "geoplanet:7.5.2", "geoplanet:7.6.0", "geoplanet:7.8.1", "geoplanet:7.9.0", "geoplanet:7.10.0", "geoplanet:8.0.0", "woeplanet:8.0.0"], "meta:indexed": "2020-08-20T20:56:28.441813", "meta:updated": "2020-10-14T12:06:59.363250", "woe:hierarchy": {"continent": 24865671, "country": 23424936, "town": 0, "planet": 1, "county": 12597449, "suburb": 0, "state": 2346874, "region": 0, "localadmin": 0}, "woe:timezone_id": 56043614, "woe:hash": "v5x9h5s9wjup", "woe:centroid": [55.729099, 64.882797], "geom:latitude": 64.882797, "geom:longitude": 55.729099, "geom:hash": "v5x9h5s9wjup", "woe:latitude": 64.882797, "geom:centroid": [55.729099, 64.882797], "woe:longitude": 55.729099, "woe:repo": "woeplanet-airport-ru", "geom:area": 0.0, "woe:scale": 19}}