{"type": "Feature", "id": 12516564, "geometry": {"type": "Point", "coordinates": [83.010201, 55.085999]}, "properties": {"woe:id": 12516564, "woe:parent_id": 2063055, "woe:name": "Novosibirsk Northeast Airport", "woe:placetype": 14, "woe:placetype_name": "Airport", "woe:lang": "ENG", "iso:country": "RU", "meta:provider": ["geoplanet:7.3.1", "geoplanet:7.3.2", "geoplanet:7.4.0", "geoplanet:7.4.1", "geoplanet:7.5.1", "geoplanet:7.5.2", "geoplanet:7.6.0", "geoplanet:7.8.1", "geoplanet:7.9.0", "geoplanet:7.10.0", "geoplanet:8.0.0", "woeplanet:8.0.0"], "meta:indexed": "2020-08-20T20:56:29.091715", "meta:updated": "2020-10-14T12:06:59.509742", "woe:hierarchy": {"continent": 24865671, "country": 23424936, "town": 0, "planet": 1, "county": 12598865, "suburb": 0, "state": 2346914, "region": 0, "localadmin": 0}, "woe:timezone_id": 56043607, "woe:hash": "vcg12un5jykp", "woe:centroid": [83.010201, 55.085999], "geom:latitude": 55.085999, "geom:longitude": 83.010201, "geom:hash": "vcg12un5jykp", "woe:latitude": 55.085999, "geom:centroid": [83.010201, 55.085999], "woe:longitude": 83.010201, "woe:repo": "woeplanet-airport-ru", "geom:area": 0.0, "woe:scale": 19}}