{"type": "Feature", "id": 12517084, "properties": {"woe:id": 12517084, "woe:parent_id": 2124437, "woe:name": "Under Construction Pevek Airport", "woe:placetype": 14, "woe:placetype_name": "Airport", "woe:lang": "ENG", "iso:country": "RU", "meta:provider": ["geoplanet:7.3.1", "geoplanet:7.3.2", "geoplanet:7.4.0", "geoplanet:7.4.1", "geoplanet:7.5.1", "geoplanet:7.5.2", "geoplanet:7.6.0", "geoplanet:7.8.1", "geoplanet:7.9.0", "geoplanet:7.10.0", "geoplanet:8.0.0", "woeplanet:8.0.0"], "meta:indexed": "2020-08-20T20:56:29.526865", "woe:alias_ENG_V": ["Under Construction Pevek", "PWE", "PWE Airport"], "meta:updated": "2020-08-22T02:53:12.337913", "woe:hierarchy": {"continent": 24865671, "country": 23424936, "town": 0, "planet": 1, "county": 12598695, "suburb": 0, "state": 20070513, "region": 0, "localadmin": 0}, "woe:timezone_id": 56043611, "woe:hash": "zu3m501yjfg2", "woe:centroid": [170.642303, 69.786201], "geom:latitude": 69.786201, "geom:longitude": 170.642303, "geom:hash": "zu3m501yjfg2", "woe:latitude": 69.786201, "geom:centroid": [170.642303, 69.786201], "woe:longitude": 170.642303, "woe:repo": "woeplanet-airport-ru"}, "geometry": {"coordinates": [170.642303, 69.786201], "type": "Point"}}