{"type": "Feature", "id": 12515886, "geometry": {"type": "Point", "coordinates": [38.471199, 66.114304]}, "properties": {"woe:id": 12515886, "woe:parent_id": 2123891, "woe:name": "Chapoma Airport", "woe:placetype": 14, "woe:placetype_name": "Airport", "woe:lang": "ENG", "iso:country": "RU", "meta:provider": ["geoplanet:7.3.1", "geoplanet:7.3.2", "geoplanet:7.4.0", "geoplanet:7.4.1", "geoplanet:7.5.1", "geoplanet:7.5.2", "geoplanet:7.6.0", "geoplanet:7.8.1", "geoplanet:7.9.0", "geoplanet:7.10.0", "geoplanet:8.0.0", "woeplanet:8.0.0"], "meta:indexed": "2020-08-20T20:56:28.468112", "meta:updated": "2020-10-14T12:06:59.353311", "woe:hierarchy": {"continent": 24865671, "country": 23424936, "town": 0, "planet": 1, "county": 12598813, "suburb": 0, "state": 2346912, "region": 0, "localadmin": 0}, "woe:timezone_id": 56043614, "woe:hash": "ugg257tzezt1", "woe:centroid": [38.471199, 66.114304], "geom:latitude": 66.114304, "geom:longitude": 38.471199, "geom:hash": "ugg257tzezt1", "woe:latitude": 66.114304, "geom:centroid": [38.471199, 66.114304], "woe:longitude": 38.471199, "woe:repo": "woeplanet-airport-ru", "geom:area": 0.0, "woe:scale": 19}}