{"type": "Feature", "id": 12517003, "properties": {"woe:id": 12517003, "woe:parent_id": 2120601, "woe:name": "Tetyukhe Airport", "woe:placetype": 14, "woe:placetype_name": "Airport", "woe:lang": "ENG", "iso:country": "RU", "meta:provider": ["geoplanet:7.3.1", "geoplanet:7.3.2", "geoplanet:7.4.0", "geoplanet:7.4.1", "geoplanet:7.5.1", "geoplanet:7.5.2", "geoplanet:7.6.0", "geoplanet:7.8.1", "geoplanet:7.9.0", "geoplanet:7.10.0", "geoplanet:8.0.0", "woeplanet:8.0.0"], "meta:indexed": "2020-08-20T20:56:29.450740", "meta:updated": "2020-08-22T02:53:12.306294", "woe:hierarchy": {"continent": 24865671, "country": 23424936, "town": 0, "planet": 1, "county": 12597905, "suburb": 0, "state": 2346886, "region": 0, "localadmin": 0}, "woe:timezone_id": 56043609, "woe:hash": "xpbm7nhxprp1", "woe:centroid": [135.489899, 44.5508], "geom:latitude": 44.5508, "geom:longitude": 135.489899, "geom:hash": "xpbm7nhxprp1", "woe:latitude": 44.5508, "geom:centroid": [135.489899, 44.5508], "woe:longitude": 135.489899, "woe:repo": "woeplanet-airport-ru"}, "geometry": {"coordinates": [135.489899, 44.5508], "type": "Point"}}