{"type": "Feature", "id": 12515977, "properties": {"woe:id": 12515977, "woe:parent_id": 2004819, "woe:name": "Fedorova Airport", "woe:placetype": 14, "woe:placetype_name": "Airport", "woe:lang": "ENG", "iso:country": "RU", "meta:provider": ["geoplanet:7.3.1", "geoplanet:7.3.2", "geoplanet:7.4.0", "geoplanet:7.4.1", "geoplanet:7.5.1", "geoplanet:7.5.2", "geoplanet:7.6.0", "geoplanet:7.8.1", "geoplanet:7.9.0", "geoplanet:7.10.0", "geoplanet:8.0.0", "woeplanet:8.0.0"], "meta:indexed": "2020-08-20T20:56:28.549446", "meta:updated": "2020-08-22T02:53:11.921903", "woe:hierarchy": {"continent": 24865671, "country": 23424936, "town": 0, "planet": 1, "county": 12599369, "suburb": 0, "state": 2346927, "region": 0, "localadmin": 0}, "woe:timezone_id": 56043614, "woe:hash": "uckfncbeyvgj", "woe:centroid": [40.727299, 52.393101], "geom:latitude": 52.393101, "geom:longitude": 40.727299, "geom:hash": "uckfncbeyvgj", "woe:latitude": 52.393101, "geom:centroid": [40.727299, 52.393101], "woe:longitude": 40.727299, "woe:repo": "woeplanet-airport-ru"}, "geometry": {"coordinates": [40.727299, 52.393101], "type": "Point"}}