{"type": "Feature", "id": 12515872, "geometry": {"type": "Point", "coordinates": [39.980801, 53.058498]}, "properties": {"woe:id": 12515872, "woe:parent_id": 2000782, "woe:name": "Bukhovoye Airport", "woe:placetype": 14, "woe:placetype_name": "Airport", "woe:lang": "ENG", "iso:country": "RU", "meta:provider": ["geoplanet:7.3.1", "geoplanet:7.3.2", "geoplanet:7.4.0", "geoplanet:7.4.1", "geoplanet:7.5.1", "geoplanet:7.5.2", "geoplanet:7.6.0", "geoplanet:7.8.1", "geoplanet:7.9.0", "geoplanet:7.10.0", "geoplanet:8.0.0", "woeplanet:8.0.0"], "meta:indexed": "2020-08-20T20:56:28.457747", "meta:updated": "2020-10-14T12:06:59.380475", "woe:hierarchy": {"continent": 24865671, "country": 23424936, "town": 0, "planet": 1, "county": 12598669, "suburb": 0, "state": 2346908, "region": 0, "localadmin": 0}, "woe:timezone_id": 56043614, "woe:hash": "uckmvg10hhvv", "woe:centroid": [39.980801, 53.058498], "geom:latitude": 53.058498, "geom:longitude": 39.980801, "geom:hash": "uckmvg10hhvv", "woe:latitude": 53.058498, "geom:centroid": [39.980801, 53.058498], "woe:longitude": 39.980801, "woe:repo": "woeplanet-airport-ru", "geom:area": 0.0, "woe:scale": 19}}