{"type": "Feature", "id": 12516287, "properties": {"woe:id": 12516287, "woe:parent_id": 2106368, "woe:name": "Kryuchkovo Airport", "woe:placetype": 14, "woe:placetype_name": "Airport", "woe:lang": "ENG", "iso:country": "RU", "meta:provider": ["geoplanet:7.3.1", "geoplanet:7.3.2", "geoplanet:7.4.0", "geoplanet:7.4.1", "geoplanet:7.5.1", "geoplanet:7.5.2", "geoplanet:7.6.0", "geoplanet:7.8.1", "geoplanet:7.9.0", "geoplanet:7.10.0", "geoplanet:8.0.0", "woeplanet:8.0.0"], "meta:indexed": "2020-08-20T20:56:28.841067", "meta:updated": "2020-08-22T02:53:12.038722", "woe:hierarchy": {"continent": 24865671, "country": 23424936, "town": 0, "planet": 1, "county": 12598363, "suburb": 0, "state": 2346898, "region": 0, "localadmin": 0}, "woe:timezone_id": 56043614, "woe:hash": "uf1hxgqwe7ns", "woe:centroid": [35.505901, 57.060001], "geom:latitude": 57.060001, "geom:longitude": 35.505901, "geom:hash": "uf1hxgqwe7ns", "woe:latitude": 57.060001, "geom:centroid": [35.505901, 57.060001], "woe:longitude": 35.505901, "woe:repo": "woeplanet-airport-ru"}, "geometry": {"coordinates": [35.505901, 57.060001], "type": "Point"}}