{"type": "Feature", "id": 12516492, "properties": {"woe:id": 12516492, "woe:parent_id": 2122387, "woe:name": "Neyvo Shaytanskiy Airport", "woe:placetype": 14, "woe:placetype_name": "Airport", "woe:lang": "ENG", "iso:country": "RU", "meta:provider": ["geoplanet:7.3.1", "geoplanet:7.3.2", "geoplanet:7.4.0", "geoplanet:7.4.1", "geoplanet:7.5.1", "geoplanet:7.5.2", "geoplanet:7.6.0", "geoplanet:7.8.1", "geoplanet:7.9.0", "geoplanet:7.10.0", "geoplanet:8.0.0", "woeplanet:8.0.0"], "meta:indexed": "2020-08-20T20:56:29.031892", "meta:updated": "2020-08-22T02:53:12.114190", "woe:hierarchy": {"continent": 24865671, "country": 23424936, "town": 0, "planet": 1, "county": 12599296, "suburb": 0, "state": 2346926, "region": 0, "localadmin": 0}, "woe:timezone_id": 28350866, "woe:hash": "v6783w0wp6yv", "woe:centroid": [61.2388, 57.7342], "geom:latitude": 57.7342, "geom:longitude": 61.2388, "geom:hash": "v6783w0wp6yv", "woe:latitude": 57.7342, "geom:centroid": [61.2388, 57.7342], "woe:longitude": 61.2388, "woe:repo": "woeplanet-airport-ru"}, "geometry": {"coordinates": [61.2388, 57.7342], "type": "Point"}}