{"type": "Feature", "id": 12516090, "geometry": {"type": "Point", "coordinates": [41.911499, 43.789001]}, "properties": {"woe:id": 12516090, "woe:parent_id": 2016401, "woe:name": "Karachayevsk Airport", "woe:placetype": 14, "woe:placetype_name": "Airport", "woe:lang": "ENG", "iso:country": "RU", "meta:provider": ["geoplanet:7.3.1", "geoplanet:7.3.2", "geoplanet:7.4.0", "geoplanet:7.4.1", "geoplanet:7.5.1", "geoplanet:7.5.2", "geoplanet:7.6.0", "geoplanet:7.8.1", "geoplanet:7.9.0", "geoplanet:7.10.0", "geoplanet:8.0.0", "woeplanet:8.0.0"], "meta:indexed": "2020-08-20T20:56:28.655546", "meta:updated": "2020-10-14T12:06:59.088533", "woe:hierarchy": {"continent": 24865671, "country": 23424936, "town": 0, "planet": 1, "county": 12597949, "suburb": 0, "state": 20070522, "region": 0, "localadmin": 0}, "woe:timezone_id": 56043614, "woe:hash": "szvc1ex12tqt", "woe:centroid": [41.911499, 43.789001], "geom:latitude": 43.789001, "geom:longitude": 41.911499, "geom:hash": "szvc1ex12tqt", "woe:latitude": 43.789001, "geom:centroid": [41.911499, 43.789001], "woe:longitude": 41.911499, "woe:repo": "woeplanet-airport-ru", "geom:area": 0.0, "woe:scale": 19}}