{"type": "Feature", "id": 12517033, "geometry": {"type": "Point", "coordinates": [46.721699, 64.883598]}, "properties": {"woe:id": 12517033, "woe:parent_id": 2123987, "woe:name": "Tsenogora Airport", "woe:placetype": 14, "woe:placetype_name": "Airport", "woe:lang": "ENG", "iso:country": "RU", "meta:provider": ["geoplanet:7.3.1", "geoplanet:7.3.2", "geoplanet:7.4.0", "geoplanet:7.4.1", "geoplanet:7.5.1", "geoplanet:7.5.2", "geoplanet:7.6.0", "geoplanet:7.8.1", "geoplanet:7.9.0", "geoplanet:7.10.0", "geoplanet:8.0.0", "woeplanet:8.0.0"], "meta:indexed": "2020-08-20T20:56:29.478421", "meta:updated": "2020-10-14T12:06:59.335340", "woe:hierarchy": {"continent": 24865671, "country": 23424936, "town": 0, "planet": 1, "county": 12598019, "suburb": 0, "state": 20070508, "region": 0, "localadmin": 0}, "woe:timezone_id": 56043614, "woe:hash": "v591p5twq7rf", "woe:centroid": [46.721699, 64.883598], "geom:latitude": 64.883598, "geom:longitude": 46.721699, "geom:hash": "v591p5twq7rf", "woe:latitude": 64.883598, "geom:centroid": [46.721699, 64.883598], "woe:longitude": 46.721699, "woe:repo": "woeplanet-airport-ru", "geom:area": 0.0, "woe:scale": 19}}