{"type": "Feature", "id": 12516559, "properties": {"woe:id": 12516559, "woe:parent_id": 2122532, "woe:name": "Novoselitskoye Airport", "woe:placetype": 14, "woe:placetype_name": "Airport", "woe:lang": "ENG", "iso:country": "RU", "meta:provider": ["geoplanet:7.3.1", "geoplanet:7.3.2", "geoplanet:7.4.0", "geoplanet:7.4.1", "geoplanet:7.5.1", "geoplanet:7.5.2", "geoplanet:7.6.0", "geoplanet:7.8.1", "geoplanet:7.9.0", "geoplanet:7.10.0", "geoplanet:8.0.0", "woeplanet:8.0.0"], "meta:indexed": "2020-08-20T20:56:29.087584", "meta:updated": "2020-08-22T02:53:12.140709", "woe:hierarchy": {"continent": 24865671, "country": 23424936, "town": 0, "planet": 1, "county": 12597966, "suburb": 0, "state": 2346887, "region": 0, "localadmin": 0}, "woe:timezone_id": 56043614, "woe:hash": "szyye9ff8t7e", "woe:centroid": [43.399799, 44.746399], "geom:latitude": 44.746399, "geom:longitude": 43.399799, "geom:hash": "szyye9ff8t7e", "woe:latitude": 44.746399, "geom:centroid": [43.399799, 44.746399], "woe:longitude": 43.399799, "woe:repo": "woeplanet-airport-ru"}, "geometry": {"coordinates": [43.399799, 44.746399], "type": "Point"}}